{
"meta":{"test_sets":[],"test_metrics":[],"learn_metrics":[{"best_value":"Min","name":"MultiClass"}],"launch_mode":"Train","parameters":"","iteration_count":1000,"learn_sets":["learn"],"name":"experiment"},
"iterations":[
{"learn":[1.726091121],"iteration":0,"passed_time":0.02634915773,"remaining_time":26.32280857},
{"learn":[1.58930623],"iteration":1,"passed_time":0.03331546045,"remaining_time":16.62441476},
{"learn":[1.455340544],"iteration":2,"passed_time":0.03979592616,"remaining_time":13.22551279},
{"learn":[1.345392931],"iteration":3,"passed_time":0.04620014129,"remaining_time":11.50383518},
{"learn":[1.256504866],"iteration":4,"passed_time":0.05186751751,"remaining_time":10.32163598},
{"learn":[1.188728009],"iteration":5,"passed_time":0.05883457023,"remaining_time":9.746927135},
{"learn":[1.11886919],"iteration":6,"passed_time":0.06461615565,"remaining_time":9.166263223},
{"learn":[1.052116673],"iteration":7,"passed_time":0.07057340906,"remaining_time":8.751102724},
{"learn":[0.9978426908],"iteration":8,"passed_time":0.07706491652,"remaining_time":8.485703586},
{"learn":[0.9444218878],"iteration":9,"passed_time":0.08359163258,"remaining_time":8.275571625},
{"learn":[0.8999316496],"iteration":10,"passed_time":0.08969701212,"remaining_time":8.064576817},
{"learn":[0.8654444293],"iteration":11,"passed_time":0.09631281218,"remaining_time":7.92975487},
{"learn":[0.8254174531],"iteration":12,"passed_time":0.1023452745,"remaining_time":7.770368148},
{"learn":[0.7887616444],"iteration":13,"passed_time":0.1089994082,"remaining_time":7.676672605},
{"learn":[0.7558085105],"iteration":14,"passed_time":0.1160731701,"remaining_time":7.622138167},
{"learn":[0.7252626317],"iteration":15,"passed_time":0.1228638881,"remaining_time":7.556129119},
{"learn":[0.6980051458],"iteration":16,"passed_time":0.12861439,"remaining_time":7.43693796},
{"learn":[0.6725131663],"iteration":17,"passed_time":0.1344454757,"remaining_time":7.334747621},
{"learn":[0.6494378204],"iteration":18,"passed_time":0.1408485242,"remaining_time":7.272231697},
{"learn":[0.6276734215],"iteration":19,"passed_time":0.1470840714,"remaining_time":7.207119498},
{"learn":[0.6084307371],"iteration":20,"passed_time":0.1532880767,"remaining_time":7.146144146},
{"learn":[0.5901558581],"iteration":21,"passed_time":0.1599389603,"remaining_time":7.110013782},
{"learn":[0.5737849153],"iteration":22,"passed_time":0.1668150957,"remaining_time":7.086015152},
{"learn":[0.5560161173],"iteration":23,"passed_time":0.1751332837,"remaining_time":7.122086869},
{"learn":[0.5426170628],"iteration":24,"passed_time":0.1821465867,"remaining_time":7.103716882},
{"learn":[0.5283359093],"iteration":25,"passed_time":0.1895488094,"remaining_time":7.100790014},
{"learn":[0.5125815276],"iteration":26,"passed_time":0.1968560314,"remaining_time":7.094108094},
{"learn":[0.5002896048],"iteration":27,"passed_time":0.2034140393,"remaining_time":7.06137308},
{"learn":[0.4885353657],"iteration":28,"passed_time":0.210373217,"remaining_time":7.043875645},
{"learn":[0.478160717],"iteration":29,"passed_time":0.2173138945,"remaining_time":7.02648259},
{"learn":[0.46816195],"iteration":30,"passed_time":0.224470032,"remaining_time":7.016498743},
{"learn":[0.4573201761],"iteration":31,"passed_time":0.2307348711,"remaining_time":6.97972985},
{"learn":[0.4474915709],"iteration":32,"passed_time":0.2374197133,"remaining_time":6.957117055},
{"learn":[0.4391573753],"iteration":33,"passed_time":0.2440310134,"remaining_time":6.933351733},
{"learn":[0.4293151909],"iteration":34,"passed_time":0.250717189,"remaining_time":6.912631067},
{"learn":[0.4196184544],"iteration":35,"passed_time":0.2574231564,"remaining_time":6.893220076},
{"learn":[0.4106040367],"iteration":36,"passed_time":0.2637699544,"remaining_time":6.865147732},
{"learn":[0.40273967],"iteration":37,"passed_time":0.2700061683,"remaining_time":6.835419313},
{"learn":[0.3958884731],"iteration":38,"passed_time":0.27684097,"remaining_time":6.82164544},
{"learn":[0.3888729632],"iteration":39,"passed_time":0.2832482685,"remaining_time":6.797958444},
{"learn":[0.3828412041],"iteration":40,"passed_time":0.2898027764,"remaining_time":6.778557624},
{"learn":[0.3761747738],"iteration":41,"passed_time":0.2965594109,"remaining_time":6.764378943},
{"learn":[0.3700510664],"iteration":42,"passed_time":0.3061733586,"remaining_time":6.814137307},
{"learn":[0.3652971089],"iteration":43,"passed_time":0.3123963641,"remaining_time":6.787521001},
{"learn":[0.3582177846],"iteration":44,"passed_time":0.3190240392,"remaining_time":6.770399054},
{"learn":[0.3531602843],"iteration":45,"passed_time":0.325248378,"remaining_time":6.745368535},
{"learn":[0.3495261137],"iteration":46,"passed_time":0.3315744259,"remaining_time":6.723200592},
{"learn":[0.3458595739],"iteration":47,"passed_time":0.3380958919,"remaining_time":6.705568522},
{"learn":[0.340340979],"iteration":48,"passed_time":0.3443308557,"remaining_time":6.682829465},
{"learn":[0.3356701749],"iteration":49,"passed_time":0.3509414057,"remaining_time":6.667886709},
{"learn":[0.3310674475],"iteration":50,"passed_time":0.3580306677,"remaining_time":6.662178503},
{"learn":[0.3269387851],"iteration":51,"passed_time":0.3645173418,"remaining_time":6.645431539},
{"learn":[0.3222472445],"iteration":52,"passed_time":0.3708608482,"remaining_time":6.626513645},
{"learn":[0.3179404559],"iteration":53,"passed_time":0.3774534814,"remaining_time":6.612425803},
{"learn":[0.3136669667],"iteration":54,"passed_time":0.3843465752,"remaining_time":6.603772974},
{"learn":[0.3100276931],"iteration":55,"passed_time":0.3909445835,"remaining_time":6.590208693},
{"learn":[0.3061277172],"iteration":56,"passed_time":0.3975986755,"remaining_time":6.577816684},
{"learn":[0.3021222546],"iteration":57,"passed_time":0.4041731002,"remaining_time":6.564328628},
{"learn":[0.2983854984],"iteration":58,"passed_time":0.4106808578,"remaining_time":6.550011648},
{"learn":[0.2947083062],"iteration":59,"passed_time":0.4170543644,"remaining_time":6.533851709},
{"learn":[0.2917230505],"iteration":60,"passed_time":0.4235857055,"remaining_time":6.520442253},
{"learn":[0.2883510807],"iteration":61,"passed_time":0.4302479642,"remaining_time":6.50923533},
{"learn":[0.2851153718],"iteration":62,"passed_time":0.4369261814,"remaining_time":6.498410032},
{"learn":[0.2820386097],"iteration":63,"passed_time":0.4431284367,"remaining_time":6.480753387},
{"learn":[0.2798158006],"iteration":64,"passed_time":0.4498918629,"remaining_time":6.471521412},
{"learn":[0.2769108251],"iteration":65,"passed_time":0.4562277442,"remaining_time":6.456313834},
{"learn":[0.2743919292],"iteration":66,"passed_time":0.4638828854,"remaining_time":6.45974227},
{"learn":[0.2711562674],"iteration":67,"passed_time":0.4713144,"remaining_time":6.459779718},
{"learn":[0.2685074216],"iteration":68,"passed_time":0.4774683216,"remaining_time":6.442362426},
{"learn":[0.2657722985],"iteration":69,"passed_time":0.4844702496,"remaining_time":6.436533316},
{"learn":[0.2633858881],"iteration":70,"passed_time":0.490864673,"remaining_time":6.42272227},
{"learn":[0.2612044478],"iteration":71,"passed_time":0.4971143869,"remaining_time":6.407252098},
{"learn":[0.2582885325],"iteration":72,"passed_time":0.5040497311,"remaining_time":6.400741105},
{"learn":[0.2555859135],"iteration":73,"passed_time":0.5116959139,"remaining_time":6.403113734},
{"learn":[0.2538436451],"iteration":74,"passed_time":0.5179545863,"remaining_time":6.388106564},
{"learn":[0.2525643281],"iteration":75,"passed_time":0.5255586438,"remaining_time":6.38968667},
{"learn":[0.2504384291],"iteration":76,"passed_time":0.5367770204,"remaining_time":6.434353115},
{"learn":[0.2483322374],"iteration":77,"passed_time":0.5701006059,"remaining_time":6.738881521},
{"learn":[0.245559646],"iteration":78,"passed_time":0.5778865815,"remaining_time":6.737133437},
{"learn":[0.2435635356],"iteration":79,"passed_time":0.5856194733,"remaining_time":6.734623943},
{"learn":[0.2413281829],"iteration":80,"passed_time":0.5931339052,"remaining_time":6.7295069},
{"learn":[0.2387539242],"iteration":81,"passed_time":0.6029132292,"remaining_time":6.749687127},
{"learn":[0.2365924902],"iteration":82,"passed_time":0.610547037,"remaining_time":6.74544136},
{"learn":[0.2350596313],"iteration":83,"passed_time":0.6187463907,"remaining_time":6.74728207},
{"learn":[0.23323719],"iteration":84,"passed_time":0.6265876167,"remaining_time":6.745031403},
{"learn":[0.2314164789],"iteration":85,"passed_time":0.6331930417,"remaining_time":6.729516745},
{"learn":[0.2290992698],"iteration":86,"passed_time":0.6394582558,"remaining_time":6.710636638},
{"learn":[0.227258762],"iteration":87,"passed_time":0.6462911408,"remaining_time":6.697926368},
{"learn":[0.225765995],"iteration":88,"passed_time":0.6527836483,"remaining_time":6.681864085},
{"learn":[0.2238950862],"iteration":89,"passed_time":0.659403865,"remaining_time":6.667305747},
{"learn":[0.2217046901],"iteration":90,"passed_time":0.6665143772,"remaining_time":6.657819438},
{"learn":[0.2196883476],"iteration":91,"passed_time":0.6748832738,"remaining_time":6.660804485},
{"learn":[0.2178953399],"iteration":92,"passed_time":0.6855598546,"remaining_time":6.686051486},
{"learn":[0.2162733881],"iteration":93,"passed_time":0.6920536121,"remaining_time":6.670218857},
{"learn":[0.2146310593],"iteration":94,"passed_time":0.6994166262,"remaining_time":6.662863649},
{"learn":[0.2130385636],"iteration":95,"passed_time":0.7068698492,"remaining_time":6.656357747},
{"learn":[0.2115940913],"iteration":96,"passed_time":0.7143708227,"remaining_time":6.650276834},
{"learn":[0.2099157582],"iteration":97,"passed_time":0.7219272549,"remaining_time":6.644677387},
{"learn":[0.2082741846],"iteration":98,"passed_time":0.7294548952,"remaining_time":6.638776369},
{"learn":[0.2070097461],"iteration":99,"passed_time":0.7366079909,"remaining_time":6.629471919},
{"learn":[0.2047152484],"iteration":100,"passed_time":0.7431651656,"remaining_time":6.614905781},
{"learn":[0.2030875251],"iteration":101,"passed_time":0.749612881,"remaining_time":6.599533011},
{"learn":[0.2010497227],"iteration":102,"passed_time":0.7559744292,"remaining_time":6.583583136},
{"learn":[0.1993280828],"iteration":103,"passed_time":0.7623264772,"remaining_time":6.567735804},
{"learn":[0.1983987633],"iteration":104,"passed_time":0.7686161498,"remaining_time":6.551537658},
{"learn":[0.1967686673],"iteration":105,"passed_time":0.7749234476,"remaining_time":6.535675114},
{"learn":[0.195546899],"iteration":106,"passed_time":0.7812592872,"remaining_time":6.520229378},
{"learn":[0.1943683623],"iteration":107,"passed_time":0.7875189179,"remaining_time":6.504322914},
{"learn":[0.1935133608],"iteration":108,"passed_time":0.7939405915,"remaining_time":6.489918046},
{"learn":[0.1920460288],"iteration":109,"passed_time":0.800699101,"remaining_time":6.478383635},
{"learn":[0.1905991175],"iteration":110,"passed_time":0.8067596885,"remaining_time":6.461345613},
{"learn":[0.1892549124],"iteration":111,"passed_time":0.8141701196,"remaining_time":6.455205948},
{"learn":[0.1879699343],"iteration":112,"passed_time":0.8204610005,"remaining_time":6.440255818},
{"learn":[0.1866187158],"iteration":113,"passed_time":0.8270590504,"remaining_time":6.427844901},
{"learn":[0.185619829],"iteration":114,"passed_time":0.8329395949,"remaining_time":6.410013405},
{"learn":[0.1844891636],"iteration":115,"passed_time":0.8389880157,"remaining_time":6.393667292},
{"learn":[0.183084093],"iteration":116,"passed_time":0.8456738163,"remaining_time":6.38230752},
{"learn":[0.1822305389],"iteration":117,"passed_time":0.8517682374,"remaining_time":6.366606656},
{"learn":[0.1813036313],"iteration":118,"passed_time":0.8582059528,"remaining_time":6.353608777},
{"learn":[0.1801251703],"iteration":119,"passed_time":0.8644630835,"remaining_time":6.339395946},
{"learn":[0.179336602],"iteration":120,"passed_time":0.8703696699,"remaining_time":6.322768098},
{"learn":[0.17829839],"iteration":121,"passed_time":0.8765926336,"remaining_time":6.308592888},
{"learn":[0.1769708612],"iteration":122,"passed_time":0.8830648493,"remaining_time":6.296324169},
{"learn":[0.1753152115],"iteration":123,"passed_time":0.8895244815,"remaining_time":6.284060047},
{"learn":[0.1739582666],"iteration":124,"passed_time":0.8966505771,"remaining_time":6.27655404},
{"learn":[0.1728735683],"iteration":125,"passed_time":0.9032037933,"remaining_time":6.265080281},
{"learn":[0.1713497538],"iteration":126,"passed_time":0.909685009,"remaining_time":6.253189078},
{"learn":[0.1698202481],"iteration":127,"passed_time":0.9160534322,"remaining_time":6.240614007},
{"learn":[0.1685638401],"iteration":128,"passed_time":0.922415522,"remaining_time":6.228092401},
{"learn":[0.1675531268],"iteration":129,"passed_time":0.9291924483,"remaining_time":6.21844177},
{"learn":[0.1663746039],"iteration":130,"passed_time":0.9353033279,"remaining_time":6.204416732},
{"learn":[0.1654167777],"iteration":131,"passed_time":0.9417853353,"remaining_time":6.192952053},
{"learn":[0.164242543],"iteration":132,"passed_time":0.9478540479,"remaining_time":6.178868117},
{"learn":[0.1631841212],"iteration":133,"passed_time":0.9539773026,"remaining_time":6.165256299},
{"learn":[0.1623807755],"iteration":134,"passed_time":0.9602846836,"remaining_time":6.152935195},
{"learn":[0.1612887128],"iteration":135,"passed_time":0.9662257286,"remaining_time":6.138375217},
{"learn":[0.1608795125],"iteration":136,"passed_time":0.9728900707,"remaining_time":6.128497307},
{"learn":[0.1601488988],"iteration":137,"passed_time":0.9816900539,"remaining_time":6.132005989},
{"learn":[0.1597981607],"iteration":138,"passed_time":0.9925007191,"remaining_time":6.147792224},
{"learn":[0.1587749688],"iteration":139,"passed_time":1.004805896,"remaining_time":6.172379073},
{"learn":[0.1579993554],"iteration":140,"passed_time":1.011902283,"remaining_time":6.164709651},
{"learn":[0.1571311127],"iteration":141,"passed_time":1.018683751,"remaining_time":6.155145479},
{"learn":[0.1565673962],"iteration":142,"passed_time":1.026151974,"remaining_time":6.149735955},
{"learn":[0.155690228],"iteration":143,"passed_time":1.0340132,"remaining_time":6.146634022},
{"learn":[0.1548145653],"iteration":144,"passed_time":1.041397214,"remaining_time":6.140652538},
{"learn":[0.1540864633],"iteration":145,"passed_time":1.047588719,"remaining_time":6.127676481},
{"learn":[0.1532670762],"iteration":146,"passed_time":1.053450014,"remaining_time":6.11287661},
{"learn":[0.1526251854],"iteration":147,"passed_time":1.060010563,"remaining_time":6.102222973},
{"learn":[0.1513345309],"iteration":148,"passed_time":1.065906233,"remaining_time":6.087826874},
{"learn":[0.1501230654],"iteration":149,"passed_time":1.072185239,"remaining_time":6.075716353},
{"learn":[0.1492075532],"iteration":150,"passed_time":1.078334452,"remaining_time":6.062953309},
{"learn":[0.1486157008],"iteration":151,"passed_time":1.084607416,"remaining_time":6.05096769},
{"learn":[0.1479771672],"iteration":152,"passed_time":1.09106384,"remaining_time":6.040072369},
{"learn":[0.1468079456],"iteration":153,"passed_time":1.097138011,"remaining_time":6.027134787},
{"learn":[0.1459476574],"iteration":154,"passed_time":1.103301516,"remaining_time":6.01477278},
{"learn":[0.1453968076],"iteration":155,"passed_time":1.109304728,"remaining_time":6.001623016},
{"learn":[0.1446520853],"iteration":156,"passed_time":1.115080522,"remaining_time":5.987343183},
{"learn":[0.1435663878],"iteration":157,"passed_time":1.12127711,"remaining_time":5.975413461},
{"learn":[0.1427415602],"iteration":158,"passed_time":1.127775243,"remaining_time":5.965150812},
{"learn":[0.1419821951],"iteration":159,"passed_time":1.133943748,"remaining_time":5.953204676},
{"learn":[0.1413109308],"iteration":160,"passed_time":1.140260796,"remaining_time":5.942104394},
{"learn":[0.1402644418],"iteration":161,"passed_time":1.146173632,"remaining_time":5.928972245},
{"learn":[0.1395306742],"iteration":162,"passed_time":1.152249428,"remaining_time":5.916765468},
{"learn":[0.1385533342],"iteration":163,"passed_time":1.158489434,"remaining_time":5.905470527},
{"learn":[0.1380680253],"iteration":164,"passed_time":1.164141101,"remaining_time":5.891259513},
{"learn":[0.1373797511],"iteration":165,"passed_time":1.170489108,"remaining_time":5.880650095},
{"learn":[0.136917597],"iteration":166,"passed_time":1.176590946,"remaining_time":5.868863818},
{"learn":[0.136299681],"iteration":167,"passed_time":1.182555824,"remaining_time":5.856466938},
{"learn":[0.1353611988],"iteration":168,"passed_time":1.189029956,"remaining_time":5.846650259},
{"learn":[0.1344314554],"iteration":169,"passed_time":1.195460463,"remaining_time":5.836659909},
{"learn":[0.133988104],"iteration":170,"passed_time":1.201831845,"remaining_time":5.826424558},
{"learn":[0.1332357482],"iteration":171,"passed_time":1.208179143,"remaining_time":5.8161182},
{"learn":[0.1325777855],"iteration":172,"passed_time":1.214433565,"remaining_time":5.805413633},
{"learn":[0.1320109398],"iteration":173,"passed_time":1.220735071,"remaining_time":5.794983729},
{"learn":[0.1311116416],"iteration":174,"passed_time":1.226840076,"remaining_time":5.783674643},
{"learn":[0.1305707978],"iteration":175,"passed_time":1.233052831,"remaining_time":5.772929164},
{"learn":[0.1298683737],"iteration":176,"passed_time":1.239071085,"remaining_time":5.761330525},
{"learn":[0.1292030946],"iteration":177,"passed_time":1.245069339,"remaining_time":5.749702227},
{"learn":[0.1284026056],"iteration":178,"passed_time":1.25141122,"remaining_time":5.739712914},
{"learn":[0.1279490785],"iteration":179,"passed_time":1.26685192,"remaining_time":5.771214303},
{"learn":[0.1272362554],"iteration":180,"passed_time":1.273163176,"remaining_time":5.760887522},
{"learn":[0.1259653828],"iteration":181,"passed_time":1.279611433,"remaining_time":5.751220619},
{"learn":[0.1252684239],"iteration":182,"passed_time":1.286182275,"remaining_time":5.742136167},
{"learn":[0.1247426943],"iteration":183,"passed_time":1.292044944,"remaining_time":5.729938448},
{"learn":[0.1243220707],"iteration":184,"passed_time":1.298045156,"remaining_time":5.718415148},
{"learn":[0.1235821089],"iteration":185,"passed_time":1.304338162,"remaining_time":5.708232603},
{"learn":[0.1229125166],"iteration":186,"passed_time":1.31068371,"remaining_time":5.698320088},
{"learn":[0.1221380822],"iteration":187,"passed_time":1.317384719,"remaining_time":5.689980809},
{"learn":[0.1214217355],"iteration":188,"passed_time":1.324048895,"remaining_time":5.681500813},
{"learn":[0.1209305878],"iteration":189,"passed_time":1.330535444,"remaining_time":5.672282682},
{"learn":[0.1202523377],"iteration":190,"passed_time":1.336929909,"remaining_time":5.662703122},
{"learn":[0.119730123],"iteration":191,"passed_time":1.343253498,"remaining_time":5.652858472},
{"learn":[0.1193013697],"iteration":192,"passed_time":1.350219134,"remaining_time":5.64573493},
{"learn":[0.1185645914],"iteration":193,"passed_time":1.359731415,"remaining_time":5.649193404},
{"learn":[0.1180898473],"iteration":194,"passed_time":1.365842378,"remaining_time":5.638477508},
{"learn":[0.1175817907],"iteration":195,"passed_time":1.372305468,"remaining_time":5.629253043},
{"learn":[0.1169100708],"iteration":196,"passed_time":1.37871935,"remaining_time":5.619856031},
{"learn":[0.1165252332],"iteration":197,"passed_time":1.384857188,"remaining_time":5.609371035},
{"learn":[0.1156158371],"iteration":198,"passed_time":1.391271362,"remaining_time":5.600042014},
{"learn":[0.1149124327],"iteration":199,"passed_time":1.397875953,"remaining_time":5.591503814},
{"learn":[0.1144352587],"iteration":200,"passed_time":1.404334419,"remaining_time":5.582403984},
{"learn":[0.1138490341],"iteration":201,"passed_time":1.410300547,"remaining_time":5.571385331},
{"learn":[0.1133235587],"iteration":202,"passed_time":1.417050099,"remaining_time":5.563492259},
{"learn":[0.1128104819],"iteration":203,"passed_time":1.423436939,"remaining_time":5.554195113},
{"learn":[0.1121539248],"iteration":204,"passed_time":1.429806695,"remaining_time":5.54486011},
{"learn":[0.1118465347],"iteration":205,"passed_time":1.438109258,"remaining_time":5.543003645},
{"learn":[0.1110875263],"iteration":206,"passed_time":1.444547348,"remaining_time":5.533942257},
{"learn":[0.110569389],"iteration":207,"passed_time":1.450976522,"remaining_time":5.524872141},
{"learn":[0.1101688953],"iteration":208,"passed_time":1.457306528,"remaining_time":5.51545198},
{"learn":[0.109677475],"iteration":209,"passed_time":1.463225031,"remaining_time":5.504513213},
{"learn":[0.1091750649],"iteration":210,"passed_time":1.469758414,"remaining_time":5.495921273},
{"learn":[0.108597669],"iteration":211,"passed_time":1.475801751,"remaining_time":5.485527265},
{"learn":[0.1076996373],"iteration":212,"passed_time":1.482137633,"remaining_time":5.476255009},
{"learn":[0.1072819571],"iteration":213,"passed_time":1.488065136,"remaining_time":5.465510266},
{"learn":[0.106839286],"iteration":214,"passed_time":1.494079181,"remaining_time":5.455126314},
{"learn":[0.1065337761],"iteration":215,"passed_time":1.50032052,"remaining_time":5.445607815},
{"learn":[0.1061222691],"iteration":216,"passed_time":1.506040522,"remaining_time":5.434238381},
{"learn":[0.1057015267],"iteration":217,"passed_time":1.512149068,"remaining_time":5.424314547},
{"learn":[0.1053899626],"iteration":218,"passed_time":1.518362782,"remaining_time":5.414800606},
{"learn":[0.1050585468],"iteration":219,"passed_time":1.524129242,"remaining_time":5.40373095},
{"learn":[0.1047676503],"iteration":220,"passed_time":1.5306195,"remaining_time":5.395260589},
{"learn":[0.1043906297],"iteration":221,"passed_time":1.536736254,"remaining_time":5.385499125},
{"learn":[0.1040625666],"iteration":222,"passed_time":1.543771349,"remaining_time":5.378970127},
{"learn":[0.1036613681],"iteration":223,"passed_time":1.550410191,"remaining_time":5.371063876},
{"learn":[0.1032294241],"iteration":224,"passed_time":1.556968824,"remaining_time":5.362892616},
{"learn":[0.1026515081],"iteration":225,"passed_time":1.56348154,"remaining_time":5.354578371},
{"learn":[0.1021305349],"iteration":226,"passed_time":1.569528877,"remaining_time":5.344695252},
{"learn":[0.1018754189],"iteration":227,"passed_time":1.575503339,"remaining_time":5.334599026},
{"learn":[0.1013880085],"iteration":228,"passed_time":1.581883263,"remaining_time":5.32590391},
{"learn":[0.100780819],"iteration":229,"passed_time":1.588223061,"remaining_time":5.317094594},
{"learn":[0.100345418],"iteration":230,"passed_time":1.594295898,"remaining_time":5.307417947},
{"learn":[0.09983236388],"iteration":231,"passed_time":1.600694988,"remaining_time":5.298852375},
{"learn":[0.09947654219],"iteration":232,"passed_time":1.606716992,"remaining_time":5.28906409},
{"learn":[0.09913175815],"iteration":233,"passed_time":1.612899039,"remaining_time":5.279831897},
{"learn":[0.09857510622],"iteration":234,"passed_time":1.619053127,"remaining_time":5.270534648},
{"learn":[0.09839192336],"iteration":235,"passed_time":1.624963547,"remaining_time":5.260475211},
{"learn":[0.09793316883],"iteration":236,"passed_time":1.631959225,"remaining_time":5.253944677},
{"learn":[0.09756975564],"iteration":237,"passed_time":1.639308697,"remaining_time":5.248542972},
{"learn":[0.09722448324],"iteration":238,"passed_time":1.645613995,"remaining_time":5.23980021},
{"learn":[0.09675837586],"iteration":239,"passed_time":1.651874667,"remaining_time":5.230936446},
{"learn":[0.09642898395],"iteration":240,"passed_time":1.657664086,"remaining_time":5.22061013},
{"learn":[0.09595328898],"iteration":241,"passed_time":1.663847841,"remaining_time":5.211556461},
{"learn":[0.09567469968],"iteration":242,"passed_time":1.66986847,"remaining_time":5.202018238},
{"learn":[0.09534538854],"iteration":243,"passed_time":1.676125434,"remaining_time":5.193241099},
{"learn":[0.09489601128],"iteration":244,"passed_time":1.68218573,"remaining_time":5.183878474},
{"learn":[0.09461905095],"iteration":245,"passed_time":1.688375818,"remaining_time":5.174940517},
{"learn":[0.09442522792],"iteration":246,"passed_time":1.694406197,"remaining_time":5.165537922},
{"learn":[0.09410017677],"iteration":247,"passed_time":1.7002732,"remaining_time":5.155667123},
{"learn":[0.093692958],"iteration":248,"passed_time":1.706306496,"remaining_time":5.146330034},
{"learn":[0.09275059047],"iteration":249,"passed_time":1.712294291,"remaining_time":5.136882873},
{"learn":[0.09245606094],"iteration":250,"passed_time":1.718427504,"remaining_time":5.127897214},
{"learn":[0.09218395632],"iteration":251,"passed_time":1.72465726,"remaining_time":5.119220755},
{"learn":[0.09192599629],"iteration":252,"passed_time":1.731318727,"remaining_time":5.111838296},
{"learn":[0.09144318128],"iteration":253,"passed_time":1.737171646,"remaining_time":5.102086803},
{"learn":[0.09111660207],"iteration":254,"passed_time":1.743521069,"remaining_time":5.093816457},
{"learn":[0.09069117872],"iteration":255,"passed_time":1.749862617,"remaining_time":5.085538231},
{"learn":[0.09023120439],"iteration":256,"passed_time":1.756065956,"remaining_time":5.076875506},
{"learn":[0.08980330248],"iteration":257,"passed_time":1.762334378,"remaining_time":5.068419025},
{"learn":[0.08947556793],"iteration":258,"passed_time":1.768655426,"remaining_time":5.060130002},
{"learn":[0.08919776405],"iteration":259,"passed_time":1.774617096,"remaining_time":5.050833273},
{"learn":[0.08851792032],"iteration":260,"passed_time":1.780907602,"remaining_time":5.042493172},
{"learn":[0.08806602926],"iteration":261,"passed_time":1.787043732,"remaining_time":5.03373387},
{"learn":[0.08737413327],"iteration":262,"passed_time":1.793409905,"remaining_time":5.025639163},
{"learn":[0.08708894865],"iteration":263,"passed_time":1.800105789,"remaining_time":5.018476745},
{"learn":[0.08664505917],"iteration":264,"passed_time":1.806788423,"remaining_time":5.011281097},
{"learn":[0.08621781776],"iteration":265,"passed_time":1.813390348,"remaining_time":5.003866599},
{"learn":[0.08597998449],"iteration":266,"passed_time":1.819588728,"remaining_time":4.995350328},
{"learn":[0.08569356178],"iteration":267,"passed_time":1.825663774,"remaining_time":4.986514487},
{"learn":[0.08540909406],"iteration":268,"passed_time":1.831756945,"remaining_time":4.977748427},
{"learn":[0.08527040281],"iteration":269,"passed_time":1.837618573,"remaining_time":4.968376141},
{"learn":[0.08480225396],"iteration":270,"passed_time":1.84387612,"remaining_time":4.960094803},
{"learn":[0.08450589257],"iteration":271,"passed_time":1.850093334,"remaining_time":4.951720394},
{"learn":[0.08421445714],"iteration":272,"passed_time":1.856273172,"remaining_time":4.943262258},
{"learn":[0.08398457012],"iteration":273,"passed_time":1.862676554,"remaining_time":4.93541306},
{"learn":[0.08350571193],"iteration":274,"passed_time":1.868859934,"remaining_time":4.926994372},
{"learn":[0.08333181842],"iteration":275,"passed_time":1.874988356,"remaining_time":4.918447716},
{"learn":[0.08299463941],"iteration":276,"passed_time":1.88108336,"remaining_time":4.909831297},
{"learn":[0.0824581766],"iteration":277,"passed_time":1.887287699,"remaining_time":4.901516973},
{"learn":[0.08198052678],"iteration":278,"passed_time":1.893553788,"remaining_time":4.893377351},
{"learn":[0.08153388639],"iteration":279,"passed_time":1.900162838,"remaining_time":4.886133012},
{"learn":[0.08123397798],"iteration":280,"passed_time":1.906259009,"remaining_time":4.877580881},
{"learn":[0.08082154125],"iteration":281,"passed_time":1.912722058,"remaining_time":4.869980275},
{"learn":[0.08044540437],"iteration":282,"passed_time":1.91871502,"remaining_time":4.861196711},
{"learn":[0.08020608559],"iteration":283,"passed_time":1.925151527,"remaining_time":4.853551033},
{"learn":[0.07981946109],"iteration":284,"passed_time":1.931475741,"remaining_time":4.845632123},
{"learn":[0.07954478429],"iteration":285,"passed_time":1.937503204,"remaining_time":4.836983523},
{"learn":[0.07922187834],"iteration":286,"passed_time":1.943745293,"remaining_time":4.828886389},
{"learn":[0.07897350621],"iteration":287,"passed_time":1.950058924,"remaining_time":4.820979006},
{"learn":[0.07881267545],"iteration":288,"passed_time":1.956491639,"remaining_time":4.813375624},
{"learn":[0.07850835684],"iteration":289,"passed_time":1.96302373,"remaining_time":4.806023615},
{"learn":[0.07823354263],"iteration":290,"passed_time":1.969715489,"remaining_time":4.799066261},
{"learn":[0.0777920072],"iteration":291,"passed_time":1.976724042,"remaining_time":4.792878842},
{"learn":[0.07745636815],"iteration":292,"passed_time":1.983015006,"remaining_time":4.784954299},
{"learn":[0.0772309734],"iteration":293,"passed_time":1.989401055,"remaining_time":4.7772692},
{"learn":[0.07690101052],"iteration":294,"passed_time":1.995786936,"remaining_time":4.769592509},
{"learn":[0.07659127298],"iteration":295,"passed_time":2.001755482,"remaining_time":4.760931956},
{"learn":[0.07630809996],"iteration":296,"passed_time":2.008878452,"remaining_time":4.75502206},
{"learn":[0.07608490462],"iteration":297,"passed_time":2.014842539,"remaining_time":4.746374035},
{"learn":[0.07590084079],"iteration":298,"passed_time":2.021197795,"remaining_time":4.738661052},
{"learn":[0.07571082921],"iteration":299,"passed_time":2.027905888,"remaining_time":4.731780405},
{"learn":[0.07546042659],"iteration":300,"passed_time":2.034687189,"remaining_time":4.725070914},
{"learn":[0.07522755407],"iteration":301,"passed_time":2.041166238,"remaining_time":4.717662365},
{"learn":[0.0749532829],"iteration":302,"passed_time":2.047468869,"remaining_time":4.709854132},
{"learn":[0.07483181773],"iteration":303,"passed_time":2.053805251,"remaining_time":4.702133074},
{"learn":[0.07453955267],"iteration":304,"passed_time":2.06100668,"remaining_time":4.696392271},
{"learn":[0.07427115628],"iteration":305,"passed_time":2.067280186,"remaining_time":4.688537415},
{"learn":[0.07396760434],"iteration":306,"passed_time":2.07376636,"remaining_time":4.681172923},
{"learn":[0.073652829],"iteration":307,"passed_time":2.080363493,"remaining_time":4.674063433},
{"learn":[0.07323553166],"iteration":308,"passed_time":2.087534381,"remaining_time":4.668240314},
{"learn":[0.07300465714],"iteration":309,"passed_time":2.093969638,"remaining_time":4.660771129},
{"learn":[0.07265070102],"iteration":310,"passed_time":2.099982142,"remaining_time":4.652372011},
{"learn":[0.07236220183],"iteration":311,"passed_time":2.106508608,"remaining_time":4.645121545},
{"learn":[0.0720933706],"iteration":312,"passed_time":2.113004115,"remaining_time":4.637807754},
{"learn":[0.07197374373],"iteration":313,"passed_time":2.124426618,"remaining_time":4.641263249},
{"learn":[0.07170835429],"iteration":314,"passed_time":2.13058054,"remaining_time":4.633167206},
{"learn":[0.07137936242],"iteration":315,"passed_time":2.13672442,"remaining_time":4.625061719},
{"learn":[0.07113537529],"iteration":316,"passed_time":2.143322803,"remaining_time":4.617947869},
{"learn":[0.0709817631],"iteration":317,"passed_time":2.149333598,"remaining_time":4.609577088},
{"learn":[0.07080943439],"iteration":318,"passed_time":2.156659029,"remaining_time":4.604027582},
{"learn":[0.07060223557],"iteration":319,"passed_time":2.16370079,"remaining_time":4.59786418},
{"learn":[0.07015200001],"iteration":320,"passed_time":2.170695052,"remaining_time":4.591594829},
{"learn":[0.0699512103],"iteration":321,"passed_time":2.177608271,"remaining_time":4.585150334},
{"learn":[0.06957660566],"iteration":322,"passed_time":2.183719317,"remaining_time":4.577021602},
{"learn":[0.06938932622],"iteration":323,"passed_time":2.191074539,"remaining_time":4.571501199},
{"learn":[0.06922262427],"iteration":324,"passed_time":2.197590964,"remaining_time":4.564227386},
{"learn":[0.0688288644],"iteration":325,"passed_time":2.20414118,"remaining_time":4.557028083},
{"learn":[0.0685988599],"iteration":326,"passed_time":2.210592979,"remaining_time":4.549630198},
{"learn":[0.06825359662],"iteration":327,"passed_time":2.217692324,"remaining_time":4.543564761},
{"learn":[0.06796132379],"iteration":328,"passed_time":2.224097206,"remaining_time":4.536076672},
{"learn":[0.06775246639],"iteration":329,"passed_time":2.230491046,"remaining_time":4.52857273},
{"learn":[0.06743791773],"iteration":330,"passed_time":2.237321848,"remaining_time":4.521958659},
{"learn":[0.06727079771],"iteration":331,"passed_time":2.24399719,"remaining_time":4.51503049},
{"learn":[0.06697892768],"iteration":332,"passed_time":2.250332738,"remaining_time":4.507423231},
{"learn":[0.0667324904],"iteration":333,"passed_time":2.257267165,"remaining_time":4.501017761},
{"learn":[0.06661405939],"iteration":334,"passed_time":2.263328919,"remaining_time":4.49287681},
{"learn":[0.06643247425],"iteration":335,"passed_time":2.270226763,"remaining_time":4.486400508},
{"learn":[0.06628493155],"iteration":336,"passed_time":2.276970148,"remaining_time":4.479617828},
{"learn":[0.06614131868],"iteration":337,"passed_time":2.293863442,"remaining_time":4.492714789},
{"learn":[0.0659781432],"iteration":338,"passed_time":2.301956712,"remaining_time":4.488476066},
{"learn":[0.06573651726],"iteration":339,"passed_time":2.30962002,"remaining_time":4.483380038},
{"learn":[0.06534294445],"iteration":340,"passed_time":2.317167369,"remaining_time":4.478044856},
{"learn":[0.06502093019],"iteration":341,"passed_time":2.32469655,"remaining_time":4.472661784},
{"learn":[0.06485029432],"iteration":342,"passed_time":2.331505644,"remaining_time":4.465886903},
{"learn":[0.06466638212],"iteration":343,"passed_time":2.33979579,"remaining_time":4.461936157},
{"learn":[0.06443708204],"iteration":344,"passed_time":2.347085553,"remaining_time":4.456060978},
{"learn":[0.06423188098],"iteration":345,"passed_time":2.353994981,"remaining_time":4.44945872},
{"learn":[0.06408799436],"iteration":346,"passed_time":2.361188618,"remaining_time":4.443389532},
{"learn":[0.06384960671],"iteration":347,"passed_time":2.36894926,"remaining_time":4.4383762},
{"learn":[0.06353869954],"iteration":348,"passed_time":2.379143004,"remaining_time":4.437885661},
{"learn":[0.06334869758],"iteration":349,"passed_time":2.397978438,"remaining_time":4.453388528},
{"learn":[0.063119941],"iteration":350,"passed_time":2.407350093,"remaining_time":4.45119718},
{"learn":[0.06284117418],"iteration":351,"passed_time":2.41579999,"remaining_time":4.447268163},
{"learn":[0.06262427915],"iteration":352,"passed_time":2.425575606,"remaining_time":4.44574339},
{"learn":[0.06234217979],"iteration":353,"passed_time":2.43210403,"remaining_time":4.438246337},
{"learn":[0.06212419456],"iteration":354,"passed_time":2.438174993,"remaining_time":4.429923578},
{"learn":[0.06175806864],"iteration":355,"passed_time":2.44426758,"remaining_time":4.421652589},
{"learn":[0.06148977754],"iteration":356,"passed_time":2.451523885,"remaining_time":4.415489799},
{"learn":[0.06130628027],"iteration":357,"passed_time":2.457735099,"remaining_time":4.407446742},
{"learn":[0.06115913081],"iteration":358,"passed_time":2.463921021,"remaining_time":4.399368731},
{"learn":[0.06111034179],"iteration":359,"passed_time":2.477561999,"remaining_time":4.404554665},
{"learn":[0.06084916458],"iteration":360,"passed_time":2.483992881,"remaining_time":4.396873825},
{"learn":[0.06065812743],"iteration":361,"passed_time":2.490179219,"remaining_time":4.388768901},
{"learn":[0.0604400567],"iteration":362,"passed_time":2.496272391,"remaining_time":4.380511054},
{"learn":[0.06027227741],"iteration":363,"passed_time":2.503078525,"remaining_time":4.37351083},
{"learn":[0.06005922164],"iteration":364,"passed_time":2.509330323,"remaining_time":4.365547274},
{"learn":[0.05978956549],"iteration":365,"passed_time":2.515647496,"remaining_time":4.357706317},
{"learn":[0.05953887173],"iteration":366,"passed_time":2.521950585,"remaining_time":4.349849374},
{"learn":[0.05928152554],"iteration":367,"passed_time":2.528488884,"remaining_time":4.342404823},
{"learn":[0.05910257384],"iteration":368,"passed_time":2.535041809,"remaining_time":4.334990194},
{"learn":[0.05884589471],"iteration":369,"passed_time":2.541541233,"remaining_time":4.327489127},
{"learn":[0.05856397313],"iteration":370,"passed_time":2.547921198,"remaining_time":4.319790926},
{"learn":[0.05836759051],"iteration":371,"passed_time":2.555893383,"remaining_time":4.314787755},
{"learn":[0.05809849709],"iteration":372,"passed_time":2.563447066,"remaining_time":4.309065175},
{"learn":[0.05788084694],"iteration":373,"passed_time":2.570809538,"remaining_time":4.303012756},
{"learn":[0.0576921333],"iteration":374,"passed_time":2.578179385,"remaining_time":4.296965642},
{"learn":[0.05745396852],"iteration":375,"passed_time":2.585192022,"remaining_time":4.290318674},
{"learn":[0.05723340512],"iteration":376,"passed_time":2.595401141,"remaining_time":4.288952018},
{"learn":[0.05700711776],"iteration":377,"passed_time":2.604165665,"remaining_time":4.285161492},
{"learn":[0.05679827576],"iteration":378,"passed_time":2.613503153,"remaining_time":4.28228353},
{"learn":[0.05658919945],"iteration":379,"passed_time":2.62213276,"remaining_time":4.278216608},
{"learn":[0.05641591587],"iteration":380,"passed_time":2.629920735,"remaining_time":4.27275836},
{"learn":[0.05631196768],"iteration":381,"passed_time":2.636398076,"remaining_time":4.265167568},
{"learn":[0.05619173713],"iteration":382,"passed_time":2.643239253,"remaining_time":4.258168718},
{"learn":[0.05598452095],"iteration":383,"passed_time":2.649808219,"remaining_time":4.250734018},
{"learn":[0.05586550197],"iteration":384,"passed_time":2.656238309,"remaining_time":4.243081975},
{"learn":[0.05576774733],"iteration":385,"passed_time":2.662346647,"remaining_time":4.23492446},
{"learn":[0.05563138252],"iteration":386,"passed_time":2.66909274,"remaining_time":4.227787725},
{"learn":[0.05549148376],"iteration":387,"passed_time":2.675320037,"remaining_time":4.219834698},
{"learn":[0.05525804395],"iteration":388,"passed_time":2.681975421,"remaining_time":4.212562936},
{"learn":[0.05510489742],"iteration":389,"passed_time":2.688323927,"remaining_time":4.204814348},
{"learn":[0.05496142585],"iteration":390,"passed_time":2.694776601,"remaining_time":4.197235166},
{"learn":[0.05475316814],"iteration":391,"passed_time":2.701104774,"remaining_time":4.189468629},
{"learn":[0.05457903644],"iteration":392,"passed_time":2.707136361,"remaining_time":4.181251326},
{"learn":[0.05437061167],"iteration":393,"passed_time":2.713652369,"remaining_time":4.173790192},
{"learn":[0.0542087973],"iteration":394,"passed_time":2.7199995,"remaining_time":4.166075184},
{"learn":[0.05394226083],"iteration":395,"passed_time":2.72613088,"remaining_time":4.158038009},
{"learn":[0.05379175292],"iteration":396,"passed_time":2.732549012,"remaining_time":4.15044598},
{"learn":[0.05366345344],"iteration":397,"passed_time":2.738941019,"remaining_time":4.142820335},
{"learn":[0.05354940763],"iteration":398,"passed_time":2.74504419,"remaining_time":4.13476581},
{"learn":[0.05337482334],"iteration":399,"passed_time":2.75143528,"remaining_time":4.12715292},
{"learn":[0.05331497413],"iteration":400,"passed_time":2.757479076,"remaining_time":4.119027347},
{"learn":[0.05316483099],"iteration":401,"passed_time":2.7640005,"remaining_time":4.111622634},
{"learn":[0.05292593517],"iteration":402,"passed_time":2.770049379,"remaining_time":4.103522281},
{"learn":[0.05261405461],"iteration":403,"passed_time":2.776503845,"remaining_time":4.096030424},
{"learn":[0.05241728726],"iteration":404,"passed_time":2.783630232,"remaining_time":4.089530834},
{"learn":[0.05224260016],"iteration":405,"passed_time":2.789948238,"remaining_time":4.081845452},
{"learn":[0.05206962629],"iteration":406,"passed_time":2.796466996,"remaining_time":4.074459284},
{"learn":[0.05190222666],"iteration":407,"passed_time":2.80297717,"remaining_time":4.067064913},
{"learn":[0.05173918381],"iteration":408,"passed_time":2.809327593,"remaining_time":4.059444028},
{"learn":[0.05160520508],"iteration":409,"passed_time":2.816381146,"remaining_time":4.052841162},
{"learn":[0.05141564021],"iteration":410,"passed_time":2.823010405,"remaining_time":4.04562805},
{"learn":[0.05129524727],"iteration":411,"passed_time":2.82946862,"remaining_time":4.038173662},
{"learn":[0.05112873104],"iteration":412,"passed_time":2.835603792,"remaining_time":4.030264953},
{"learn":[0.0510447981],"iteration":413,"passed_time":2.842031507,"remaining_time":4.022778896},
{"learn":[0.05093841853],"iteration":414,"passed_time":2.848927601,"remaining_time":4.015958184},
{"learn":[0.05067739907],"iteration":415,"passed_time":2.855149731,"remaining_time":4.008190969},
{"learn":[0.05050342889],"iteration":416,"passed_time":2.86151478,"remaining_time":4.000630975},
{"learn":[0.05038768971],"iteration":417,"passed_time":2.867814452,"remaining_time":3.992985673},
{"learn":[0.05025055813],"iteration":418,"passed_time":2.873989082,"remaining_time":3.985173405},
{"learn":[0.05008011974],"iteration":419,"passed_time":2.880422048,"remaining_time":3.977725685},
{"learn":[0.04995194265],"iteration":420,"passed_time":2.886559427,"remaining_time":3.969876267},
{"learn":[0.04983335189],"iteration":421,"passed_time":2.893139394,"remaining_time":3.96264116},
{"learn":[0.04969255333],"iteration":422,"passed_time":2.899763444,"remaining_time":3.955469284},
{"learn":[0.04951552609],"iteration":423,"passed_time":2.906188159,"remaining_time":3.948029197},
{"learn":[0.04936219739],"iteration":424,"passed_time":2.91295446,"remaining_time":3.941056035},
{"learn":[0.04923789228],"iteration":425,"passed_time":2.919500343,"remaining_time":3.933786848},
{"learn":[0.04910085841],"iteration":426,"passed_time":2.925751974,"remaining_time":3.926126185},
{"learn":[0.04900420413],"iteration":427,"passed_time":2.931984354,"remaining_time":3.91844638},
{"learn":[0.04887609966],"iteration":428,"passed_time":2.938285402,"remaining_time":3.910864719},
{"learn":[0.04873881817],"iteration":429,"passed_time":2.944691826,"remaining_time":3.903428699},
{"learn":[0.04851697626],"iteration":430,"passed_time":2.95163842,"remaining_time":3.896710582},
{"learn":[0.04841831998],"iteration":431,"passed_time":2.957994218,"remaining_time":3.88921462},
{"learn":[0.04830631976],"iteration":432,"passed_time":2.964719269,"remaining_time":3.882207449},
{"learn":[0.04824643993],"iteration":433,"passed_time":2.97081844,"remaining_time":3.874385339},
{"learn":[0.04814898411],"iteration":434,"passed_time":2.976965278,"remaining_time":3.866633062},
{"learn":[0.04798552428],"iteration":435,"passed_time":2.983085116,"remaining_time":3.858853224},
{"learn":[0.04787064964],"iteration":436,"passed_time":2.989426872,"remaining_time":3.851366886},
{"learn":[0.04765986765],"iteration":437,"passed_time":2.995612836,"remaining_time":3.843685876},
{"learn":[0.0475294657],"iteration":438,"passed_time":3.001967634,"remaining_time":3.836227432},
{"learn":[0.04741765477],"iteration":439,"passed_time":3.008459642,"remaining_time":3.828948635},
{"learn":[0.04728392417],"iteration":440,"passed_time":3.014540438,"remaining_time":3.821152165},
{"learn":[0.04714748772],"iteration":441,"passed_time":3.020774485,"remaining_time":3.813556929},
{"learn":[0.04706855393],"iteration":442,"passed_time":3.027216033,"remaining_time":3.806228737},
{"learn":[0.04693897651],"iteration":443,"passed_time":3.033575748,"remaining_time":3.798802063},
{"learn":[0.04683094397],"iteration":444,"passed_time":3.039668919,"remaining_time":3.791047753},
{"learn":[0.04669607957],"iteration":445,"passed_time":3.046203094,"remaining_time":3.783848686},
{"learn":[0.04655795137],"iteration":446,"passed_time":3.052567225,"remaining_time":3.776442227},
{"learn":[0.04635757223],"iteration":447,"passed_time":3.05953182,"remaining_time":3.769780278},
{"learn":[0.04624032651],"iteration":448,"passed_time":3.066253037,"remaining_time":3.762818315},
{"learn":[0.04611115465],"iteration":449,"passed_time":3.07251496,"remaining_time":3.755296062},
{"learn":[0.04598379963],"iteration":450,"passed_time":3.078981675,"remaining_time":3.748028691},
{"learn":[0.04589080681],"iteration":451,"passed_time":3.087319197,"remaining_time":3.743033008},
{"learn":[0.04574275594],"iteration":452,"passed_time":3.094393208,"remaining_time":3.736496876},
{"learn":[0.04562380236],"iteration":453,"passed_time":3.100897049,"remaining_time":3.729272663},
{"learn":[0.04553825461],"iteration":454,"passed_time":3.108291147,"remaining_time":3.723117967},
{"learn":[0.04537705227],"iteration":455,"passed_time":3.114674445,"remaining_time":3.71575197},
{"learn":[0.04525980395],"iteration":456,"passed_time":3.121363288,"remaining_time":3.708753315},
{"learn":[0.04518046416],"iteration":457,"passed_time":3.130797484,"remaining_time":3.705004883},
{"learn":[0.045071153],"iteration":458,"passed_time":3.137316367,"remaining_time":3.697795543},
{"learn":[0.04497454271],"iteration":459,"passed_time":3.14343233,"remaining_time":3.690116213},
{"learn":[0.04481145849],"iteration":460,"passed_time":3.149696752,"remaining_time":3.682617244},
{"learn":[0.04462394603],"iteration":461,"passed_time":3.156372344,"remaining_time":3.675602427},
{"learn":[0.0445474385],"iteration":462,"passed_time":3.162847935,"remaining_time":3.668357108},
{"learn":[0.04440617734],"iteration":463,"passed_time":3.170602952,"remaining_time":3.662593065},
{"learn":[0.04427275796],"iteration":464,"passed_time":3.177179002,"remaining_time":3.655464013},
{"learn":[0.04412677425],"iteration":465,"passed_time":3.184068179,"remaining_time":3.648696153},
{"learn":[0.0440208114],"iteration":466,"passed_time":3.191256608,"remaining_time":3.642269319},
{"learn":[0.04392163126],"iteration":467,"passed_time":3.198507121,"remaining_time":3.635909805},
{"learn":[0.04377064818],"iteration":468,"passed_time":3.205753926,"remaining_time":3.629542292},
{"learn":[0.0436920614],"iteration":469,"passed_time":3.213741112,"remaining_time":3.624005934},
{"learn":[0.04358761938],"iteration":470,"passed_time":3.220559288,"remaining_time":3.617146207},
{"learn":[0.043424292],"iteration":471,"passed_time":3.227329381,"remaining_time":3.610232867},
{"learn":[0.04332161175],"iteration":472,"passed_time":3.234145683,"remaining_time":3.603371617},
{"learn":[0.04322216318],"iteration":473,"passed_time":3.240532273,"remaining_time":3.596033703},
{"learn":[0.04314411722],"iteration":474,"passed_time":3.246942655,"remaining_time":3.588726092},
{"learn":[0.04302643531],"iteration":475,"passed_time":3.253299744,"remaining_time":3.581363584},
{"learn":[0.04293605896],"iteration":476,"passed_time":3.259461499,"remaining_time":3.57379112},
{"learn":[0.04281400628],"iteration":477,"passed_time":3.265856714,"remaining_time":3.566479508},
{"learn":[0.0427552112],"iteration":478,"passed_time":3.272159929,"remaining_time":3.559071655},
{"learn":[0.04262193896],"iteration":479,"passed_time":3.278408476,"remaining_time":3.551609182},
{"learn":[0.04252324329],"iteration":480,"passed_time":3.284733149,"remaining_time":3.544233897},
{"learn":[0.04239702887],"iteration":481,"passed_time":3.291070239,"remaining_time":3.536876314},
{"learn":[0.04227865068],"iteration":482,"passed_time":3.29737137,"remaining_time":3.529484468},
{"learn":[0.04221330739],"iteration":483,"passed_time":3.303812002,"remaining_time":3.522245853},
{"learn":[0.04208482288],"iteration":484,"passed_time":3.310275551,"remaining_time":3.515034863},
{"learn":[0.04192581647],"iteration":485,"passed_time":3.316849975,"remaining_time":3.507944213},
{"learn":[0.04184887602],"iteration":486,"passed_time":3.323273524,"remaining_time":3.500696751},
{"learn":[0.0417172086],"iteration":487,"passed_time":3.329714406,"remaining_time":3.493470852},
{"learn":[0.04159657155],"iteration":488,"passed_time":3.336398707,"remaining_time":3.486502534},
{"learn":[0.04153466403],"iteration":489,"passed_time":3.342736838,"remaining_time":3.479175076},
{"learn":[0.04145362089],"iteration":490,"passed_time":3.34937718,"remaining_time":3.472164938},
{"learn":[0.04138394819],"iteration":491,"passed_time":3.355850229,"remaining_time":3.46498357},
{"learn":[0.04125435327],"iteration":492,"passed_time":3.361933483,"remaining_time":3.457404211},
{"learn":[0.04116054412],"iteration":493,"passed_time":3.368602784,"remaining_time":3.450431191},
{"learn":[0.04109663184],"iteration":494,"passed_time":3.374650579,"remaining_time":3.442825339},
{"learn":[0.04096588541],"iteration":495,"passed_time":3.381401047,"remaining_time":3.435939774},
{"learn":[0.04089463361],"iteration":496,"passed_time":3.387953472,"remaining_time":3.428854318},
{"learn":[0.04081592964],"iteration":497,"passed_time":3.394500938,"remaining_time":3.421766006},
{"learn":[0.04070390886],"iteration":498,"passed_time":3.401307573,"remaining_time":3.414940068},
{"learn":[0.04063027901],"iteration":499,"passed_time":3.408861838,"remaining_time":3.408861838},
{"learn":[0.04056834092],"iteration":500,"passed_time":3.416496688,"remaining_time":3.402857978},
{"learn":[0.040533149],"iteration":501,"passed_time":3.42290507,"remaining_time":3.395630926},
{"learn":[0.0404024008],"iteration":502,"passed_time":3.429415035,"remaining_time":3.3885075},
{"learn":[0.04025016971],"iteration":503,"passed_time":3.435957877,"remaining_time":3.381418863},
{"learn":[0.04018951496],"iteration":504,"passed_time":3.442438051,"remaining_time":3.374270961},
{"learn":[0.04002946716],"iteration":505,"passed_time":3.449074643,"remaining_time":3.367278406},
{"learn":[0.03993131069],"iteration":506,"passed_time":3.455414357,"remaining_time":3.359998576},
{"learn":[0.03982653714],"iteration":507,"passed_time":3.461853948,"remaining_time":3.352819178},
{"learn":[0.03967890399],"iteration":508,"passed_time":3.468499915,"remaining_time":3.345841764},
{"learn":[0.03958483912],"iteration":509,"passed_time":3.475037589,"remaining_time":3.338761605},
{"learn":[0.03950346453],"iteration":510,"passed_time":3.481504763,"remaining_time":3.331616104},
{"learn":[0.03939068427],"iteration":511,"passed_time":3.487813436,"remaining_time":3.324322181},
{"learn":[0.0392932341],"iteration":512,"passed_time":3.494850781,"remaining_time":3.31772384},
{"learn":[0.03915783127],"iteration":513,"passed_time":3.501348246,"remaining_time":3.310613323},
{"learn":[0.03905332409],"iteration":514,"passed_time":3.507625002,"remaining_time":3.303297332},
{"learn":[0.03900683914],"iteration":515,"passed_time":3.513856383,"remaining_time":3.295942809},
{"learn":[0.03895173909],"iteration":516,"passed_time":3.520281598,"remaining_time":3.288773717},
{"learn":[0.03886380231],"iteration":517,"passed_time":3.526484062,"remaining_time":3.281400227},
{"learn":[0.03870750098],"iteration":518,"passed_time":3.532971694,"remaining_time":3.274295539},
{"learn":[0.03856766576],"iteration":519,"passed_time":3.539333159,"remaining_time":3.267076762},
{"learn":[0.03847452822],"iteration":520,"passed_time":3.545723999,"remaining_time":3.259888283},
{"learn":[0.03838394006],"iteration":521,"passed_time":3.552035172,"remaining_time":3.252629908},
{"learn":[0.03835316529],"iteration":522,"passed_time":3.55848072,"remaining_time":3.245497713},
{"learn":[0.03825326329],"iteration":523,"passed_time":3.564918144,"remaining_time":3.238360757},
{"learn":[0.03818008161],"iteration":524,"passed_time":3.571313901,"remaining_time":3.231188768},
{"learn":[0.03811182938],"iteration":525,"passed_time":3.577664574,"remaining_time":3.223979103},
{"learn":[0.03800608513],"iteration":526,"passed_time":3.583719495,"remaining_time":3.216507251},
{"learn":[0.0379473611],"iteration":527,"passed_time":3.589793957,"remaining_time":3.209058235},
{"learn":[0.03789245118],"iteration":528,"passed_time":3.596546259,"remaining_time":3.202217935},
{"learn":[0.03778303146],"iteration":529,"passed_time":3.602712597,"remaining_time":3.194858341},
{"learn":[0.03771054895],"iteration":530,"passed_time":3.608937102,"remaining_time":3.187554616},
{"learn":[0.03757099203],"iteration":531,"passed_time":3.615366234,"remaining_time":3.180434958},
{"learn":[0.03751555199],"iteration":532,"passed_time":3.62268329,"remaining_time":3.174095865},
{"learn":[0.03739271445],"iteration":533,"passed_time":3.630340014,"remaining_time":3.168049526},
{"learn":[0.03733441268],"iteration":534,"passed_time":3.637352984,"remaining_time":3.16143764},
{"learn":[0.03721696776],"iteration":535,"passed_time":3.643883033,"remaining_time":3.154406208},
{"learn":[0.03713778192],"iteration":536,"passed_time":3.649988371,"remaining_time":3.147010458},
{"learn":[0.03700229664],"iteration":537,"passed_time":3.656683005,"remaining_time":3.140125555},
{"learn":[0.03686241198],"iteration":538,"passed_time":3.663122971,"remaining_time":3.133023543},
{"learn":[0.03679710924],"iteration":539,"passed_time":3.669432352,"remaining_time":3.125812744},
{"learn":[0.03669653748],"iteration":540,"passed_time":3.676350029,"remaining_time":3.119121374},
{"learn":[0.03660847007],"iteration":541,"passed_time":3.683019871,"remaining_time":3.112219744},
{"learn":[0.03654223417],"iteration":542,"passed_time":3.689565462,"remaining_time":3.105214395},
{"learn":[0.0364708512],"iteration":543,"passed_time":3.695937677,"remaining_time":3.098065406},
{"learn":[0.03637733809],"iteration":544,"passed_time":3.702270975,"remaining_time":3.090886778},
{"learn":[0.03628339727],"iteration":545,"passed_time":3.709336279,"remaining_time":3.084319909},
{"learn":[0.03618328233],"iteration":546,"passed_time":3.715898203,"remaining_time":3.077334344},
{"learn":[0.03606003791],"iteration":547,"passed_time":3.722271585,"remaining_time":3.070194811},
{"learn":[0.03597191739],"iteration":548,"passed_time":3.729105012,"remaining_time":3.063435993},
{"learn":[0.03588799302],"iteration":549,"passed_time":3.735417559,"remaining_time":3.05625073},
{"learn":[0.03581173781],"iteration":550,"passed_time":3.741893358,"remaining_time":3.049201666},
{"learn":[0.03573575809],"iteration":551,"passed_time":3.747941863,"remaining_time":3.041807888},
{"learn":[0.03562910967],"iteration":552,"passed_time":3.754819706,"remaining_time":3.035089347},
{"learn":[0.03559394857],"iteration":553,"passed_time":3.761677383,"remaining_time":3.028353994},
{"learn":[0.03550344069],"iteration":554,"passed_time":3.767952514,"remaining_time":3.021151115},
{"learn":[0.03546435895],"iteration":555,"passed_time":3.776067367,"remaining_time":3.015420703},
{"learn":[0.03534504501],"iteration":556,"passed_time":3.782424207,"remaining_time":3.008283525},
{"learn":[0.03522495436],"iteration":557,"passed_time":3.789266175,"remaining_time":3.001533422},
{"learn":[0.03513785418],"iteration":558,"passed_time":3.795950018,"remaining_time":2.994658243},
{"learn":[0.03504595513],"iteration":559,"passed_time":3.802239107,"remaining_time":2.987473584},
{"learn":[0.0349586683],"iteration":560,"passed_time":3.808946449,"remaining_time":2.980619414},
{"learn":[0.03491332721],"iteration":561,"passed_time":3.815115454,"remaining_time":2.973346208},
{"learn":[0.0348294495],"iteration":562,"passed_time":3.822045923,"remaining_time":2.966667972},
{"learn":[0.03471278804],"iteration":563,"passed_time":3.828756766,"remaining_time":2.95981906},
{"learn":[0.03466897995],"iteration":564,"passed_time":3.83569411,"remaining_time":2.953145023},
{"learn":[0.03459107006],"iteration":565,"passed_time":3.842179409,"remaining_time":2.946123434},
{"learn":[0.03453114214],"iteration":566,"passed_time":3.848392414,"remaining_time":2.938895794},
{"learn":[0.03446062389],"iteration":567,"passed_time":3.854803838,"remaining_time":2.931822637},
{"learn":[0.0344136208],"iteration":568,"passed_time":3.861120511,"remaining_time":2.924680035},
{"learn":[0.03433164277],"iteration":569,"passed_time":3.867004014,"remaining_time":2.917213554},
{"learn":[0.03427343291],"iteration":570,"passed_time":3.87311531,"remaining_time":2.909923762},
{"learn":[0.03418609853],"iteration":571,"passed_time":3.879736152,"remaining_time":2.903019358},
{"learn":[0.03411371182],"iteration":572,"passed_time":3.88592899,"remaining_time":2.895796996},
{"learn":[0.03403029908],"iteration":573,"passed_time":3.892197204,"remaining_time":2.888634162},
{"learn":[0.03393402122],"iteration":574,"passed_time":3.898423668,"remaining_time":2.881443581},
{"learn":[0.03385296284],"iteration":575,"passed_time":3.905391012,"remaining_time":2.874801717},
{"learn":[0.03377936077],"iteration":576,"passed_time":3.91174406,"remaining_time":2.867708384},
{"learn":[0.03373614736],"iteration":577,"passed_time":3.917777814,"remaining_time":2.860384494},
{"learn":[0.03365891011],"iteration":578,"passed_time":3.92428403,"remaining_time":2.853408595},
{"learn":[0.03359229796],"iteration":579,"passed_time":3.930490494,"remaining_time":2.846217254},
{"learn":[0.03353883606],"iteration":580,"passed_time":3.936492206,"remaining_time":2.838881643},
{"learn":[0.03346459476],"iteration":581,"passed_time":3.94272192,"remaining_time":2.831714369},
{"learn":[0.0333820865],"iteration":582,"passed_time":3.948904175,"remaining_time":2.824516365},
{"learn":[0.03331330322],"iteration":583,"passed_time":3.955091055,"remaining_time":2.817325135},
{"learn":[0.03325594182],"iteration":584,"passed_time":3.96102235,"remaining_time":2.809956026},
{"learn":[0.03313662582],"iteration":585,"passed_time":3.967414232,"remaining_time":2.802917222},
{"learn":[0.03302714709],"iteration":586,"passed_time":3.974142741,"remaining_time":2.796117465},
{"learn":[0.03296442887],"iteration":587,"passed_time":3.980414663,"remaining_time":2.78899803},
{"learn":[0.03291734404],"iteration":588,"passed_time":3.987042922,"remaining_time":2.78213012},
{"learn":[0.03285079972],"iteration":589,"passed_time":3.993720056,"remaining_time":2.775296988},
{"learn":[0.03277539516],"iteration":590,"passed_time":4.001014194,"remaining_time":2.76889138},
{"learn":[0.03269771933],"iteration":591,"passed_time":4.007357909,"remaining_time":2.761827748},
{"learn":[0.03267754635],"iteration":592,"passed_time":4.013306287,"remaining_time":2.754495209},
{"learn":[0.0326318647],"iteration":593,"passed_time":4.019668669,"remaining_time":2.747450302},
{"learn":[0.0325482014],"iteration":594,"passed_time":4.026363928,"remaining_time":2.74063427},
{"learn":[0.0324863281],"iteration":595,"passed_time":4.032765601,"remaining_time":2.733619636},
{"learn":[0.03244847239],"iteration":596,"passed_time":4.03607821,"remaining_time":2.724521807},
{"learn":[0.03240446762],"iteration":597,"passed_time":4.042379507,"remaining_time":2.717452445},
{"learn":[0.03235874101],"iteration":598,"passed_time":4.04844922,"remaining_time":2.710230613},
{"learn":[0.03225551762],"iteration":599,"passed_time":4.054544766,"remaining_time":2.703029844},
{"learn":[0.03221549829],"iteration":600,"passed_time":4.060743271,"remaining_time":2.695901107},
{"learn":[0.03215732272],"iteration":601,"passed_time":4.066960152,"remaining_time":2.688787609},
{"learn":[0.03206076188],"iteration":602,"passed_time":4.073123115,"remaining_time":2.681641587},
{"learn":[0.03202525483],"iteration":603,"passed_time":4.079065993,"remaining_time":2.674354525},
{"learn":[0.03194885031],"iteration":604,"passed_time":4.085264707,"remaining_time":2.667238941},
{"learn":[0.03186238073],"iteration":605,"passed_time":4.091264669,"remaining_time":2.659997161},
{"learn":[0.03177891841],"iteration":606,"passed_time":4.097354423,"remaining_time":2.652817609},
{"learn":[0.03172130876],"iteration":607,"passed_time":4.103522345,"remaining_time":2.645692038},
{"learn":[0.03163450986],"iteration":608,"passed_time":4.109594474,"remaining_time":2.638508111},
{"learn":[0.03158509215],"iteration":609,"passed_time":4.115837813,"remaining_time":2.63143729},
{"learn":[0.03154325209],"iteration":610,"passed_time":4.122202861,"remaining_time":2.624446666},
{"learn":[0.03150000997],"iteration":611,"passed_time":4.128416158,"remaining_time":2.617361878},
{"learn":[0.03145439389],"iteration":612,"passed_time":4.134400579,"remaining_time":2.610135439},
{"learn":[0.03136833111],"iteration":613,"passed_time":4.140798961,"remaining_time":2.603173288},
{"learn":[0.03130046349],"iteration":614,"passed_time":4.146978882,"remaining_time":2.596076211},
{"learn":[0.03119300235],"iteration":615,"passed_time":4.156236327,"remaining_time":2.590900568},
{"learn":[0.031117035],"iteration":616,"passed_time":4.163421882,"remaining_time":2.584425576},
{"learn":[0.03106238772],"iteration":617,"passed_time":4.17004614,"remaining_time":2.577601336},
{"learn":[0.03096706658],"iteration":618,"passed_time":4.17641223,"remaining_time":2.570618836},
{"learn":[0.03092896434],"iteration":619,"passed_time":4.182991405,"remaining_time":2.563768926},
{"learn":[0.03087520645],"iteration":620,"passed_time":4.189912749,"remaining_time":2.557128715},
{"learn":[0.03082103241],"iteration":621,"passed_time":4.197017136,"remaining_time":2.550598838},
{"learn":[0.03075151218],"iteration":622,"passed_time":4.204145023,"remaining_time":2.544081338},
{"learn":[0.03070773315],"iteration":623,"passed_time":4.210342903,"remaining_time":2.537001493},
{"learn":[0.03063515145],"iteration":624,"passed_time":4.217116746,"remaining_time":2.530270048},
{"learn":[0.03058019317],"iteration":625,"passed_time":4.223840006,"remaining_time":2.523508246},
{"learn":[0.03046740106],"iteration":626,"passed_time":4.230684016,"remaining_time":2.516818402},
{"learn":[0.03040322446],"iteration":627,"passed_time":4.237497192,"remaining_time":2.510109802},
{"learn":[0.03034411978],"iteration":628,"passed_time":4.244221701,"remaining_time":2.503348571},
{"learn":[0.03030592753],"iteration":629,"passed_time":4.25080571,"remaining_time":2.496504941},
{"learn":[0.03025444719],"iteration":630,"passed_time":4.257196425,"remaining_time":2.489549098},
{"learn":[0.03018557158],"iteration":631,"passed_time":4.26562278,"remaining_time":2.483780353},
{"learn":[0.03012832685],"iteration":632,"passed_time":4.273696841,"remaining_time":2.477798958},
{"learn":[0.03008393341],"iteration":633,"passed_time":4.281578026,"remaining_time":2.471699617},
{"learn":[0.03002697185],"iteration":634,"passed_time":4.288681871,"remaining_time":2.465147847},
{"learn":[0.02998340022],"iteration":635,"passed_time":4.296724057,"remaining_time":2.459131379},
{"learn":[0.0299497045],"iteration":636,"passed_time":4.304103988,"remaining_time":2.452731158},
{"learn":[0.02985210309],"iteration":637,"passed_time":4.313092889,"remaining_time":2.447240793},
{"learn":[0.02978879757],"iteration":638,"passed_time":4.323557969,"remaining_time":2.442573438},
{"learn":[0.02972197557],"iteration":639,"passed_time":4.334510426,"remaining_time":2.438162115},
{"learn":[0.02965304113],"iteration":640,"passed_time":4.343350077,"remaining_time":2.432547079},
{"learn":[0.02961272898],"iteration":641,"passed_time":4.352351603,"remaining_time":2.427012265},
{"learn":[0.02955613925],"iteration":642,"passed_time":4.359543699,"remaining_time":2.420462054},
{"learn":[0.02952186375],"iteration":643,"passed_time":4.366540877,"remaining_time":2.4138021},
{"learn":[0.02946138328],"iteration":644,"passed_time":4.373682098,"remaining_time":2.407220379},
{"learn":[0.02941628969],"iteration":645,"passed_time":4.380556108,"remaining_time":2.400490499},
{"learn":[0.0293602897],"iteration":646,"passed_time":4.388687628,"remaining_time":2.394446264},
{"learn":[0.02935006676],"iteration":647,"passed_time":4.395653556,"remaining_time":2.387762425},
{"learn":[0.02927938282],"iteration":648,"passed_time":4.403623699,"remaining_time":2.38162083},
{"learn":[0.02925793611],"iteration":649,"passed_time":4.411233299,"remaining_time":2.375279469},
{"learn":[0.02919206289],"iteration":650,"passed_time":4.419207734,"remaining_time":2.369129799},
{"learn":[0.0291533209],"iteration":651,"passed_time":4.427257628,"remaining_time":2.363014808},
{"learn":[0.02909172535],"iteration":652,"passed_time":4.442594869,"remaining_time":2.360766339},
{"learn":[0.02904039133],"iteration":653,"passed_time":4.449466171,"remaining_time":2.353998922},
{"learn":[0.02898622425],"iteration":654,"passed_time":4.458254071,"remaining_time":2.348240694},
{"learn":[0.02889519267],"iteration":655,"passed_time":4.466318757,"remaining_time":2.342093982},
{"learn":[0.0288060224],"iteration":656,"passed_time":4.474322901,"remaining_time":2.335909825},
{"learn":[0.02875361624],"iteration":657,"passed_time":4.482192211,"remaining_time":2.329650055},
{"learn":[0.02871340317],"iteration":658,"passed_time":4.488636801,"remaining_time":2.322648178},
{"learn":[0.02867095198],"iteration":659,"passed_time":4.498550543,"remaining_time":2.317435128},
{"learn":[0.0286292762],"iteration":660,"passed_time":4.505124384,"remaining_time":2.310494956},
{"learn":[0.02860348266],"iteration":661,"passed_time":4.511351431,"remaining_time":2.303378827},
{"learn":[0.02855152573],"iteration":662,"passed_time":4.517291018,"remaining_time":2.296119266},
{"learn":[0.02851156391],"iteration":663,"passed_time":4.523404606,"remaining_time":2.288951728},
{"learn":[0.0284762432],"iteration":664,"passed_time":4.528968398,"remaining_time":2.281510396},
{"learn":[0.02844001595],"iteration":665,"passed_time":4.535260821,"remaining_time":2.274440111},
{"learn":[0.02837230856],"iteration":666,"passed_time":4.541890412,"remaining_time":2.267540491},
{"learn":[0.02832045204],"iteration":667,"passed_time":4.54772679,"remaining_time":2.260247446},
{"learn":[0.02828111892],"iteration":668,"passed_time":4.554457591,"remaining_time":2.253401289},
{"learn":[0.02823307979],"iteration":669,"passed_time":4.560573762,"remaining_time":2.246252749},
{"learn":[0.02818436431],"iteration":670,"passed_time":4.568073111,"remaining_time":2.239785474},
{"learn":[0.02812374767],"iteration":671,"passed_time":4.573724945,"remaining_time":2.232413366},
{"learn":[0.02807320006],"iteration":672,"passed_time":4.580032826,"remaining_time":2.225365132},
{"learn":[0.02799795222],"iteration":673,"passed_time":4.587631134,"remaining_time":2.218943249},
{"learn":[0.02797709412],"iteration":674,"passed_time":4.594906647,"remaining_time":2.21236246},
{"learn":[0.02793476085],"iteration":675,"passed_time":4.622709024,"remaining_time":2.215617935},
{"learn":[0.0278778128],"iteration":676,"passed_time":4.628949946,"remaining_time":2.208494583},
{"learn":[0.02780861639],"iteration":677,"passed_time":4.635001075,"remaining_time":2.201283697},
{"learn":[0.02777364621],"iteration":678,"passed_time":4.64068616,"remaining_time":2.193903177},
{"learn":[0.02773111599],"iteration":679,"passed_time":4.648852305,"remaining_time":2.187695202},
{"learn":[0.02767720056],"iteration":680,"passed_time":4.66865408,"remaining_time":2.186931941},
{"learn":[0.02764082381],"iteration":681,"passed_time":4.675288964,"remaining_time":2.179973446},
{"learn":[0.02759500977],"iteration":682,"passed_time":4.68253781,"remaining_time":2.173300858},
{"learn":[0.02753870761],"iteration":683,"passed_time":4.689110152,"remaining_time":2.166314047},
{"learn":[0.02749917832],"iteration":684,"passed_time":4.697172879,"remaining_time":2.160013806},
{"learn":[0.0274513857],"iteration":685,"passed_time":4.704206099,"remaining_time":2.153237194},
{"learn":[0.02740898515],"iteration":686,"passed_time":4.711292444,"remaining_time":2.146484039},
{"learn":[0.02738153599],"iteration":687,"passed_time":4.73824994,"remaining_time":2.148741252},
{"learn":[0.02733016664],"iteration":688,"passed_time":4.744628197,"remaining_time":2.141624629},
{"learn":[0.02727861578],"iteration":689,"passed_time":4.801284,"remaining_time":2.157098609},
{"learn":[0.02721427033],"iteration":690,"passed_time":4.810398861,"remaining_time":2.151104556},
{"learn":[0.0271325387],"iteration":691,"passed_time":4.82235966,"remaining_time":2.146368172},
{"learn":[0.0270586332],"iteration":692,"passed_time":4.832547862,"remaining_time":2.140825676},
{"learn":[0.02701558259],"iteration":693,"passed_time":4.840275837,"remaining_time":2.134185023},
{"learn":[0.02698421858],"iteration":694,"passed_time":4.848508774,"remaining_time":2.127762843},
{"learn":[0.02693387994],"iteration":695,"passed_time":4.85413815,"remaining_time":2.120198273},
{"learn":[0.02690447956],"iteration":696,"passed_time":4.859911777,"remaining_time":2.112701963},
{"learn":[0.026867725],"iteration":697,"passed_time":4.867781045,"remaining_time":2.1061173},
{"learn":[0.02682314497],"iteration":698,"passed_time":4.876064816,"remaining_time":2.099707453},
{"learn":[0.0267779079],"iteration":699,"passed_time":4.907578388,"remaining_time":2.103247881},
{"learn":[0.02671200832],"iteration":700,"passed_time":4.982834416,"remaining_time":2.125345921},
{"learn":[0.02666580246],"iteration":701,"passed_time":4.992430114,"remaining_time":2.119293695},
{"learn":[0.02661810857],"iteration":702,"passed_time":5.002889943,"remaining_time":2.113596462},
{"learn":[0.02656150668],"iteration":703,"passed_time":5.014451072,"remaining_time":2.108348746},
{"learn":[0.02651859352],"iteration":704,"passed_time":5.028957557,"remaining_time":2.104315573},
{"learn":[0.02648302078],"iteration":705,"passed_time":5.037995125,"remaining_time":2.097975307},
{"learn":[0.0263965098],"iteration":706,"passed_time":5.052496068,"remaining_time":2.093891581},
{"learn":[0.0263266146],"iteration":707,"passed_time":5.060597213,"remaining_time":2.087138963},
{"learn":[0.02627589186],"iteration":708,"passed_time":5.068404772,"remaining_time":2.080262043},
{"learn":[0.02623126132],"iteration":709,"passed_time":5.077163463,"remaining_time":2.073770992},
{"learn":[0.02618564863],"iteration":710,"passed_time":5.086423117,"remaining_time":2.067477188},
{"learn":[0.02613119606],"iteration":711,"passed_time":5.096534318,"remaining_time":2.061519499},
{"learn":[0.02610271592],"iteration":712,"passed_time":5.108226115,"remaining_time":2.056186388},
{"learn":[0.02605636474],"iteration":713,"passed_time":5.116792013,"remaining_time":2.049583355},
{"learn":[0.02599994388],"iteration":714,"passed_time":5.124412196,"remaining_time":2.042597868},
{"learn":[0.02596612815],"iteration":715,"passed_time":5.141867036,"remaining_time":2.039511506},
{"learn":[0.02591609199],"iteration":716,"passed_time":5.152590034,"remaining_time":2.033728005},
{"learn":[0.02588483759],"iteration":717,"passed_time":5.172673519,"remaining_time":2.031607148},
{"learn":[0.02584479956],"iteration":718,"passed_time":5.180353869,"remaining_time":2.024588925},
{"learn":[0.02578574504],"iteration":719,"passed_time":5.187542673,"remaining_time":2.017377706},
{"learn":[0.02575661972],"iteration":720,"passed_time":5.197866793,"remaining_time":2.011379799},
{"learn":[0.02570954251],"iteration":721,"passed_time":5.207400615,"remaining_time":2.005065611},
{"learn":[0.02565922498],"iteration":722,"passed_time":5.215074673,"remaining_time":1.998029992},
{"learn":[0.02558732232],"iteration":723,"passed_time":5.222414646,"remaining_time":1.990865252},
{"learn":[0.02555724554],"iteration":724,"passed_time":5.231321338,"remaining_time":1.984294301},
{"learn":[0.02550440398],"iteration":725,"passed_time":5.239499858,"remaining_time":1.977442095},
{"learn":[0.0254693139],"iteration":726,"passed_time":5.246944956,"remaining_time":1.97031083},
{"learn":[0.02539965276],"iteration":727,"passed_time":5.253293921,"remaining_time":1.962769157},
{"learn":[0.02535071628],"iteration":728,"passed_time":5.260997188,"remaining_time":1.955734208},
{"learn":[0.02530431352],"iteration":729,"passed_time":5.267595529,"remaining_time":1.948288757},
{"learn":[0.02524195265],"iteration":730,"passed_time":5.274326913,"remaining_time":1.940894582},
{"learn":[0.02520609687],"iteration":731,"passed_time":5.281219424,"remaining_time":1.93356121},
{"learn":[0.0251701874],"iteration":732,"passed_time":5.288250394,"remaining_time":1.926279475},
{"learn":[0.02513057797],"iteration":733,"passed_time":5.295891077,"remaining_time":1.919219382},
{"learn":[0.02506822753],"iteration":734,"passed_time":5.306628491,"remaining_time":1.913274218},
{"learn":[0.02503802376],"iteration":735,"passed_time":5.313043915,"remaining_time":1.905765752},
{"learn":[0.02501223131],"iteration":736,"passed_time":5.320269844,"remaining_time":1.898549483},
{"learn":[0.02496519952],"iteration":737,"passed_time":5.328648533,"remaining_time":1.891742433},
{"learn":[0.02489291664],"iteration":738,"passed_time":5.335919421,"remaining_time":1.884539877},
{"learn":[0.02483213781],"iteration":739,"passed_time":5.346472459,"remaining_time":1.878490324},
{"learn":[0.02479805881],"iteration":740,"passed_time":5.353327345,"remaining_time":1.871136008},
{"learn":[0.02476773516],"iteration":741,"passed_time":5.377175692,"remaining_time":1.869691817},
{"learn":[0.02470187358],"iteration":742,"passed_time":5.396661339,"remaining_time":1.866678283},
{"learn":[0.02464830994],"iteration":743,"passed_time":5.406512039,"remaining_time":1.860305218},
{"learn":[0.02461723752],"iteration":744,"passed_time":5.414460557,"remaining_time":1.853271734},
{"learn":[0.02456991164],"iteration":745,"passed_time":5.424693426,"remaining_time":1.847013579},
{"learn":[0.02452242409],"iteration":746,"passed_time":5.433909663,"remaining_time":1.840400461},
{"learn":[0.02445769185],"iteration":747,"passed_time":5.443505402,"remaining_time":1.833908237},
{"learn":[0.02444302396],"iteration":748,"passed_time":5.451860215,"remaining_time":1.826991875},
{"learn":[0.0244134641],"iteration":749,"passed_time":5.461027243,"remaining_time":1.820342414},
{"learn":[0.02435538074],"iteration":750,"passed_time":5.469658017,"remaining_time":1.81350845},
{"learn":[0.02430760632],"iteration":751,"passed_time":5.482142194,"remaining_time":1.807940511},
{"learn":[0.02427748591],"iteration":752,"passed_time":5.494222494,"remaining_time":1.802221721},
{"learn":[0.0242417588],"iteration":753,"passed_time":5.503685524,"remaining_time":1.795632147},
{"learn":[0.02420298668],"iteration":754,"passed_time":5.512501174,"remaining_time":1.788824884},
{"learn":[0.02416817937],"iteration":755,"passed_time":5.531992655,"remaining_time":1.785457947},
{"learn":[0.02412844284],"iteration":756,"passed_time":5.54036376,"remaining_time":1.778478724},
{"learn":[0.02404834475],"iteration":757,"passed_time":5.548725365,"remaining_time":1.771492795},
{"learn":[0.02401310635],"iteration":758,"passed_time":5.556283006,"remaining_time":1.764247964},
{"learn":[0.02396498314],"iteration":759,"passed_time":5.563226975,"remaining_time":1.756808518},
{"learn":[0.02392328861],"iteration":760,"passed_time":5.570207361,"remaining_time":1.749381812},
{"learn":[0.02387115955],"iteration":761,"passed_time":5.576445241,"remaining_time":1.741724367},
{"learn":[0.02384633767],"iteration":762,"passed_time":5.582715622,"remaining_time":1.734080737},
{"learn":[0.02379935498],"iteration":763,"passed_time":5.588487708,"remaining_time":1.726286779},
{"learn":[0.02377025917],"iteration":764,"passed_time":5.594644004,"remaining_time":1.718616132},
{"learn":[0.02374395322],"iteration":765,"passed_time":5.601933976,"remaining_time":1.711295758},
{"learn":[0.02370526134],"iteration":766,"passed_time":5.608239815,"remaining_time":1.703676502},
{"learn":[0.0236732724],"iteration":767,"passed_time":5.614143902,"remaining_time":1.695939304},
{"learn":[0.02363850573],"iteration":768,"passed_time":5.621407082,"remaining_time":1.688615131},
{"learn":[0.02360917076],"iteration":769,"passed_time":5.628009465,"remaining_time":1.681093736},
{"learn":[0.02356298129],"iteration":770,"passed_time":5.635390312,"remaining_time":1.673805942},
{"learn":[0.02349646533],"iteration":771,"passed_time":5.642536617,"remaining_time":1.666448638},
{"learn":[0.02346966658],"iteration":772,"passed_time":5.649312335,"remaining_time":1.658983053},
{"learn":[0.02343309282],"iteration":773,"passed_time":5.661777554,"remaining_time":1.653180526},
{"learn":[0.02339745038],"iteration":774,"passed_time":5.670420244,"remaining_time":1.646251039},
{"learn":[0.02333996683],"iteration":775,"passed_time":5.677065045,"remaining_time":1.638740425},
{"learn":[0.0232802575],"iteration":776,"passed_time":5.684201974,"remaining_time":1.631373282},
{"learn":[0.02324541743],"iteration":777,"passed_time":5.690803857,"remaining_time":1.623854057},
{"learn":[0.02319396207],"iteration":778,"passed_time":5.697267114,"remaining_time":1.616297859},
{"learn":[0.02316696891],"iteration":779,"passed_time":5.703912123,"remaining_time":1.608795727},
{"learn":[0.02313783299],"iteration":780,"passed_time":5.710025127,"remaining_time":1.601146611},
{"learn":[0.02309770018],"iteration":781,"passed_time":5.716850304,"remaining_time":1.593699957},
{"learn":[0.02305402586],"iteration":782,"passed_time":5.722868766,"remaining_time":1.586031318},
{"learn":[0.02302974309],"iteration":783,"passed_time":5.72908323,"remaining_time":1.57842089},
{"learn":[0.02300217115],"iteration":784,"passed_time":5.735771405,"remaining_time":1.570943761},
{"learn":[0.02296101565],"iteration":785,"passed_time":5.741874035,"remaining_time":1.563309216},
{"learn":[0.02291205459],"iteration":786,"passed_time":5.749419134,"remaining_time":1.556068965},
{"learn":[0.02289926215],"iteration":787,"passed_time":5.755836141,"remaining_time":1.548524444},
{"learn":[0.02286504989],"iteration":788,"passed_time":5.763750909,"remaining_time":1.541383323},
{"learn":[0.02284488708],"iteration":789,"passed_time":5.770591002,"remaining_time":1.53395457},
{"learn":[0.02282452889],"iteration":790,"passed_time":5.772416766,"remaining_time":1.525202407},
{"learn":[0.02278699359],"iteration":791,"passed_time":5.778936024,"remaining_time":1.51770037},
{"learn":[0.02272766523],"iteration":792,"passed_time":5.79116395,"remaining_time":1.511690968},
{"learn":[0.02267029368],"iteration":793,"passed_time":5.800878356,"remaining_time":1.50501378},
{"learn":[0.02265002154],"iteration":794,"passed_time":5.808555456,"remaining_time":1.497803608},
{"learn":[0.02261195739],"iteration":795,"passed_time":5.818652491,"remaining_time":1.491212447},
{"learn":[0.02257680773],"iteration":796,"passed_time":5.826233382,"remaining_time":1.483971614},
{"learn":[0.02254253841],"iteration":797,"passed_time":5.834914989,"remaining_time":1.477008556},
{"learn":[0.02249988372],"iteration":798,"passed_time":5.844693438,"remaining_time":1.470317123},
{"learn":[0.02247023744],"iteration":799,"passed_time":5.853329795,"remaining_time":1.463332449},
{"learn":[0.02243367337],"iteration":800,"passed_time":5.861280272,"remaining_time":1.456173251},
{"learn":[0.02239302729],"iteration":801,"passed_time":5.868341784,"remaining_time":1.44879261},
{"learn":[0.02233048444],"iteration":802,"passed_time":5.876099551,"remaining_time":1.441583576},
{"learn":[0.022298684],"iteration":803,"passed_time":5.884455822,"remaining_time":1.434519081},
{"learn":[0.02227291007],"iteration":804,"passed_time":5.891906545,"remaining_time":1.42723202},
{"learn":[0.02226238368],"iteration":805,"passed_time":5.89979148,"remaining_time":1.420049066},
{"learn":[0.02221679123],"iteration":806,"passed_time":5.907013243,"remaining_time":1.412705769},
{"learn":[0.02218707182],"iteration":807,"passed_time":5.91481126,"remaining_time":1.405499705},
{"learn":[0.0221688369],"iteration":808,"passed_time":5.92116585,"remaining_time":1.397951394},
{"learn":[0.02211491992],"iteration":809,"passed_time":5.92845478,"remaining_time":1.390625195},
{"learn":[0.02206960595],"iteration":810,"passed_time":5.935314332,"remaining_time":1.383199024},
{"learn":[0.02202204314],"iteration":811,"passed_time":5.941900924,"remaining_time":1.375711051},
{"learn":[0.02197773691],"iteration":812,"passed_time":5.949286188,"remaining_time":1.368409},
{"learn":[0.02193731118],"iteration":813,"passed_time":5.956284533,"remaining_time":1.361018333},
{"learn":[0.0219130833],"iteration":814,"passed_time":5.963744922,"remaining_time":1.35373351},
{"learn":[0.02187346357],"iteration":815,"passed_time":5.97007222,"remaining_time":1.346192756},
{"learn":[0.0218376488],"iteration":816,"passed_time":5.976008348,"remaining_time":1.338567353},
{"learn":[0.02180060659],"iteration":817,"passed_time":5.982718608,"remaining_time":1.331118321},
{"learn":[0.02177696572],"iteration":818,"passed_time":5.98922349,"remaining_time":1.323625704},
{"learn":[0.02175093256],"iteration":819,"passed_time":5.996080917,"remaining_time":1.316212884},
{"learn":[0.02170393232],"iteration":820,"passed_time":6.003405056,"remaining_time":1.308903173},
{"learn":[0.02166168093],"iteration":821,"passed_time":6.0103889,"remaining_time":1.301519738},
{"learn":[0.02162770994],"iteration":822,"passed_time":6.017044242,"remaining_time":1.294066623},
{"learn":[0.02161048526],"iteration":823,"passed_time":6.023546792,"remaining_time":1.28658281},
{"learn":[0.02157234217],"iteration":824,"passed_time":6.030428094,"remaining_time":1.279181717},
{"learn":[0.02154456996],"iteration":825,"passed_time":6.045451791,"remaining_time":1.273497108},
{"learn":[0.02149284904],"iteration":826,"passed_time":6.088048363,"remaining_time":1.27355788},
{"learn":[0.02146866741],"iteration":827,"passed_time":6.099484866,"remaining_time":1.26704275},
{"learn":[0.02141862173],"iteration":828,"passed_time":6.110036196,"remaining_time":1.26033316},
{"learn":[0.02137865041],"iteration":829,"passed_time":6.12307067,"remaining_time":1.254122908},
{"learn":[0.02135108731],"iteration":830,"passed_time":6.155902585,"remaining_time":1.251922427},
{"learn":[0.0213162777],"iteration":831,"passed_time":6.169174435,"remaining_time":1.245698684},
{"learn":[0.02127804118],"iteration":832,"passed_time":6.177287872,"remaining_time":1.238423859},
{"learn":[0.02126246507],"iteration":833,"passed_time":6.185508476,"remaining_time":1.231168354},
{"learn":[0.02123166948],"iteration":834,"passed_time":6.193171659,"remaining_time":1.223800388},
{"learn":[0.02119869288],"iteration":835,"passed_time":6.200728466,"remaining_time":1.216410847},
{"learn":[0.02117416725],"iteration":836,"passed_time":6.208168397,"remaining_time":1.208998147},
{"learn":[0.02115378515],"iteration":837,"passed_time":6.219991986,"remaining_time":1.202432818},
{"learn":[0.02113119615],"iteration":838,"passed_time":6.228752094,"remaining_time":1.195267088},
{"learn":[0.02109388489],"iteration":839,"passed_time":6.238170957,"remaining_time":1.188223039},
{"learn":[0.02105776717],"iteration":840,"passed_time":6.248068699,"remaining_time":1.18126388},
{"learn":[0.02102749906],"iteration":841,"passed_time":6.259476994,"remaining_time":1.174581194},
{"learn":[0.0209880633],"iteration":842,"passed_time":6.271540168,"remaining_time":1.16800926},
{"learn":[0.02095516081],"iteration":843,"passed_time":6.279616563,"remaining_time":1.160687422},
{"learn":[0.02092065268],"iteration":844,"passed_time":6.286696866,"remaining_time":1.153181082},
{"learn":[0.02089972738],"iteration":845,"passed_time":6.293871087,"remaining_time":1.145692846},
{"learn":[0.02087478153],"iteration":846,"passed_time":6.301101059,"remaining_time":1.138215421},
{"learn":[0.02085169101],"iteration":847,"passed_time":6.308208737,"remaining_time":1.13071666},
{"learn":[0.02082871484],"iteration":848,"passed_time":6.316392341,"remaining_time":1.123410181},
{"learn":[0.02079816201],"iteration":849,"passed_time":6.329806609,"remaining_time":1.117024696},
{"learn":[0.0207550456],"iteration":850,"passed_time":6.338291382,"remaining_time":1.109759596},
{"learn":[0.02072660035],"iteration":851,"passed_time":6.347772745,"remaining_time":1.102664749},
{"learn":[0.02071177776],"iteration":852,"passed_time":6.355428261,"remaining_time":1.095249653},
{"learn":[0.02067229358],"iteration":853,"passed_time":6.364753832,"remaining_time":1.088119508},
{"learn":[0.02063638033],"iteration":854,"passed_time":6.37992553,"remaining_time":1.081975675},
{"learn":[0.02060402907],"iteration":855,"passed_time":6.395194937,"remaining_time":1.075827186},
{"learn":[0.02058159655],"iteration":856,"passed_time":6.415418299,"remaining_time":1.070484034},
{"learn":[0.02055502505],"iteration":857,"passed_time":6.433024349,"remaining_time":1.064673027},
{"learn":[0.0205150971],"iteration":858,"passed_time":6.443777555,"remaining_time":1.057709703},
{"learn":[0.02049726036],"iteration":859,"passed_time":6.464526879,"remaining_time":1.052364841},
{"learn":[0.02046393208],"iteration":860,"passed_time":6.478921613,"remaining_time":1.045958309},
{"learn":[0.02045057043],"iteration":861,"passed_time":6.488684395,"remaining_time":1.038791701},
{"learn":[0.02042306393],"iteration":862,"passed_time":6.510402726,"remaining_time":1.033517003},
{"learn":[0.02039198402],"iteration":863,"passed_time":6.527398396,"remaining_time":1.027460859},
{"learn":[0.02035105487],"iteration":864,"passed_time":6.539604572,"remaining_time":1.020631927},
{"learn":[0.02033353794],"iteration":865,"passed_time":6.559950226,"remaining_time":1.015050035},
{"learn":[0.02028756425],"iteration":866,"passed_time":6.575037673,"remaining_time":1.008627463},
{"learn":[0.02026938316],"iteration":867,"passed_time":6.634331205,"remaining_time":1.00890751},
{"learn":[0.02025042342],"iteration":868,"passed_time":6.690201128,"remaining_time":1.008534347},
{"learn":[0.02022157289],"iteration":869,"passed_time":6.744261287,"remaining_time":1.007763181},
{"learn":[0.02017001975],"iteration":870,"passed_time":6.751276549,"remaining_time":0.9999020376},
{"learn":[0.02014377437],"iteration":871,"passed_time":6.76269976,"remaining_time":0.992689873},
{"learn":[0.02013215671],"iteration":872,"passed_time":6.77331234,"remaining_time":0.9853501343},
{"learn":[0.02010637777],"iteration":873,"passed_time":6.782406326,"remaining_time":0.9777839783},
{"learn":[0.02008292564],"iteration":874,"passed_time":6.789863382,"remaining_time":0.9699804832},
{"learn":[0.02005214975],"iteration":875,"passed_time":6.7977219,"remaining_time":0.9622346069},
{"learn":[0.0200192206],"iteration":876,"passed_time":6.806533842,"remaining_time":0.9546221922},
{"learn":[0.01997867919],"iteration":877,"passed_time":6.819739233,"remaining_time":0.9476175245},
{"learn":[0.0199539341],"iteration":878,"passed_time":6.83114832,"remaining_time":0.9403514752},
{"learn":[0.0199429431],"iteration":879,"passed_time":6.840957394,"remaining_time":0.9328578264},
{"learn":[0.01992173768],"iteration":880,"passed_time":6.848801953,"remaining_time":0.9250935669},
{"learn":[0.01989051592],"iteration":881,"passed_time":6.857696937,"remaining_time":0.9174696583},
{"learn":[0.01986766893],"iteration":882,"passed_time":6.866382461,"remaining_time":0.9098151166},
{"learn":[0.01984090565],"iteration":883,"passed_time":6.874225812,"remaining_time":0.902047731},
{"learn":[0.01983186776],"iteration":884,"passed_time":6.881724911,"remaining_time":0.8942354404},
{"learn":[0.01978699733],"iteration":885,"passed_time":6.889513511,"remaining_time":0.8864611064},
{"learn":[0.0197627099],"iteration":886,"passed_time":6.896866942,"remaining_time":0.8786313015},
{"learn":[0.01973468678],"iteration":887,"passed_time":6.90612322,"remaining_time":0.8710425683},
{"learn":[0.01971585747],"iteration":888,"passed_time":6.915259206,"remaining_time":0.863435064},
{"learn":[0.01968439279],"iteration":889,"passed_time":6.92456686,"remaining_time":0.8558453422},
{"learn":[0.01965955998],"iteration":890,"passed_time":6.932300627,"remaining_time":0.8480592237},
{"learn":[0.01964237945],"iteration":891,"passed_time":6.950773267,"remaining_time":0.8415734448},
{"learn":[0.01961089524],"iteration":892,"passed_time":6.966078299,"remaining_time":0.8346812744},
{"learn":[0.01958654616],"iteration":893,"passed_time":6.974416987,"remaining_time":0.826944296},
{"learn":[0.01955755125],"iteration":894,"passed_time":6.981463166,"remaining_time":0.8190543379},
{"learn":[0.01953819554],"iteration":895,"passed_time":6.987698004,"remaining_time":0.8110720898},
{"learn":[0.01949497242],"iteration":896,"passed_time":6.994999185,"remaining_time":0.8032161829},
{"learn":[0.01947037724],"iteration":897,"passed_time":7.003268747,"remaining_time":0.7954715058},
{"learn":[0.01942100417],"iteration":898,"passed_time":7.014714084,"remaining_time":0.7880824499},
{"learn":[0.01940222318],"iteration":899,"passed_time":7.020701046,"remaining_time":0.780077894},
{"learn":[0.01939238825],"iteration":900,"passed_time":7.027662682,"remaining_time":0.7721849118},
{"learn":[0.01935256912],"iteration":901,"passed_time":7.034111647,"remaining_time":0.7642382943},
{"learn":[0.01932410086],"iteration":902,"passed_time":7.041515537,"remaining_time":0.7563975715},
{"learn":[0.01930251213],"iteration":903,"passed_time":7.047952752,"remaining_time":0.7484551595},
{"learn":[0.01926935675],"iteration":904,"passed_time":7.055277682,"remaining_time":0.7406092595},
{"learn":[0.01924950778],"iteration":905,"passed_time":7.062341403,"remaining_time":0.7327374082},
{"learn":[0.01921856497],"iteration":906,"passed_time":7.070045419,"remaining_time":0.7249329923},
{"learn":[0.01918894209],"iteration":907,"passed_time":7.07656576,"remaining_time":0.7170088656},
{"learn":[0.01914672414],"iteration":908,"passed_time":7.08361223,"remaining_time":0.7091404983},
{"learn":[0.01913660433],"iteration":909,"passed_time":7.091953043,"remaining_time":0.7014019493},
{"learn":[0.01911809279],"iteration":910,"passed_time":7.098753762,"remaining_time":0.6935116189},
{"learn":[0.01909690749],"iteration":911,"passed_time":7.105773606,"remaining_time":0.6856448217},
{"learn":[0.01906385595],"iteration":912,"passed_time":7.114319379,"remaining_time":0.6779252859},
{"learn":[0.01903421878],"iteration":913,"passed_time":7.122194189,"remaining_time":0.6701408099},
{"learn":[0.01899677249],"iteration":914,"passed_time":7.129489869,"remaining_time":0.6623023376},
{"learn":[0.018977392],"iteration":915,"passed_time":7.136710507,"remaining_time":0.6544581688},
{"learn":[0.01895508208],"iteration":916,"passed_time":7.143336807,"remaining_time":0.6465615649},
{"learn":[0.01893467392],"iteration":917,"passed_time":7.15005315,"remaining_time":0.6386757715},
{"learn":[0.01892155764],"iteration":918,"passed_time":7.157122412,"remaining_time":0.6308236293},
{"learn":[0.01889777708],"iteration":919,"passed_time":7.16841458,"remaining_time":0.6233403983},
{"learn":[0.01888136863],"iteration":920,"passed_time":7.175113048,"remaining_time":0.6154548651},
{"learn":[0.01885086543],"iteration":921,"passed_time":7.181807265,"remaining_time":0.6075715474},
{"learn":[0.01882090939],"iteration":922,"passed_time":7.188553108,"remaining_time":0.599695113},
{"learn":[0.01879746143],"iteration":923,"passed_time":7.195556369,"remaining_time":0.5918422988},
{"learn":[0.01876218016],"iteration":924,"passed_time":7.202121377,"remaining_time":0.5839557873},
{"learn":[0.01873769455],"iteration":925,"passed_time":7.209379057,"remaining_time":0.576127484},
{"learn":[0.01871135829],"iteration":926,"passed_time":7.215514603,"remaining_time":0.5682120454},
{"learn":[0.01867432931],"iteration":927,"passed_time":7.222770158,"remaining_time":0.5603873399},
{"learn":[0.01865972327],"iteration":928,"passed_time":7.229393,"remaining_time":0.5525155038},
{"learn":[0.01862882527],"iteration":929,"passed_time":7.235951175,"remaining_time":0.5446414863},
{"learn":[0.01861278223],"iteration":930,"passed_time":7.242228389,"remaining_time":0.5367494724},
{"learn":[0.01859474363],"iteration":931,"passed_time":7.248669979,"remaining_time":0.5288729169},
{"learn":[0.01856757396],"iteration":932,"passed_time":7.255578948,"remaining_time":0.5210330006},
{"learn":[0.01854777238],"iteration":933,"passed_time":7.262395083,"remaining_time":0.5131885177},
{"learn":[0.01850771059],"iteration":934,"passed_time":7.268949924,"remaining_time":0.5053280696},
{"learn":[0.01847552441],"iteration":935,"passed_time":7.27561235,"remaining_time":0.4974777675},
{"learn":[0.01845652598],"iteration":936,"passed_time":7.282023565,"remaining_time":0.4896131106},
{"learn":[0.01841464717],"iteration":937,"passed_time":7.288784325,"remaining_time":0.4817746568},
{"learn":[0.01839019492],"iteration":938,"passed_time":7.295506042,"remaining_time":0.4739359623},
{"learn":[0.01834609783],"iteration":939,"passed_time":7.302695846,"remaining_time":0.4661295221},
{"learn":[0.01832220409],"iteration":940,"passed_time":7.309380105,"remaining_time":0.4582926952},
{"learn":[0.01829432776],"iteration":941,"passed_time":7.316206449,"remaining_time":0.4504670637},
{"learn":[0.01828154627],"iteration":942,"passed_time":7.323760173,"remaining_time":0.4426875184},
{"learn":[0.01825671479],"iteration":943,"passed_time":7.33161769,"remaining_time":0.4349264732},
{"learn":[0.01823720097],"iteration":944,"passed_time":7.347991231,"remaining_time":0.4276608653},
{"learn":[0.01821608749],"iteration":945,"passed_time":7.354626864,"remaining_time":0.4198201381},
{"learn":[0.01819904788],"iteration":946,"passed_time":7.361549792,"remaining_time":0.4119980348},
{"learn":[0.01817811277],"iteration":947,"passed_time":7.36816755,"remaining_time":0.4041610893},
{"learn":[0.01814954429],"iteration":948,"passed_time":7.374707725,"remaining_time":0.3963225437},
{"learn":[0.01812186391],"iteration":949,"passed_time":7.381104523,"remaining_time":0.3884791854},
{"learn":[0.01810246135],"iteration":950,"passed_time":7.38757378,"remaining_time":0.3806426028},
{"learn":[0.0180824605],"iteration":951,"passed_time":7.394770168,"remaining_time":0.3728455547},
{"learn":[0.01805584643],"iteration":952,"passed_time":7.404063322,"remaining_time":0.3651531754},
{"learn":[0.01799856326],"iteration":953,"passed_time":7.411315168,"remaining_time":0.3573590123},
{"learn":[0.01796409325],"iteration":954,"passed_time":7.417754551,"remaining_time":0.3495277013},
{"learn":[0.01792888044],"iteration":955,"passed_time":7.424245641,"remaining_time":0.3417016822},
{"learn":[0.01789599334],"iteration":956,"passed_time":7.433851172,"remaining_time":0.3340183912},
{"learn":[0.01789034351],"iteration":957,"passed_time":7.443235327,"remaining_time":0.3263213818},
{"learn":[0.01787449528],"iteration":958,"passed_time":7.450591091,"remaining_time":0.3185341342},
{"learn":[0.01785220829],"iteration":959,"passed_time":7.458311274,"remaining_time":0.3107629698},
{"learn":[0.01783932701],"iteration":960,"passed_time":7.464885407,"remaining_time":0.3029454015},
{"learn":[0.0178232678],"iteration":961,"passed_time":7.471794668,"remaining_time":0.2951436563},
{"learn":[0.01781257594],"iteration":962,"passed_time":7.478412218,"remaining_time":0.2873325567},
{"learn":[0.01778864526],"iteration":963,"passed_time":7.485514105,"remaining_time":0.2795420205},
{"learn":[0.01777269425],"iteration":964,"passed_time":7.494215796,"remaining_time":0.2718109356},
{"learn":[0.01774426006],"iteration":965,"passed_time":7.500791846,"remaining_time":0.2640030256},
{"learn":[0.01771341993],"iteration":966,"passed_time":7.507598855,"remaining_time":0.2562055452},
{"learn":[0.01769409961],"iteration":967,"passed_time":7.514838869,"remaining_time":0.2484244254},
{"learn":[0.01766990628],"iteration":968,"passed_time":7.521854672,"remaining_time":0.2406372496},
{"learn":[0.01764860068],"iteration":969,"passed_time":7.528501347,"remaining_time":0.2328402478},
{"learn":[0.01762859377],"iteration":970,"passed_time":7.535103522,"remaining_time":0.2250442864},
{"learn":[0.01760059476],"iteration":971,"passed_time":7.542010199,"remaining_time":0.2172595531},
{"learn":[0.01758359395],"iteration":972,"passed_time":7.548619499,"remaining_time":0.2094683725},
{"learn":[0.01756727353],"iteration":973,"passed_time":7.554837213,"remaining_time":0.2016691658},
{"learn":[0.01754105806],"iteration":974,"passed_time":7.56151893,"remaining_time":0.1938851008},
{"learn":[0.01752405907],"iteration":975,"passed_time":7.567888728,"remaining_time":0.1860956245},
{"learn":[0.01749403267],"iteration":976,"passed_time":7.576652336,"remaining_time":0.1783654081},
{"learn":[0.01747483062],"iteration":977,"passed_time":7.58306576,"remaining_time":0.1705802114},
{"learn":[0.01743572436],"iteration":978,"passed_time":7.589657101,"remaining_time":0.1628016334},
{"learn":[0.01741152261],"iteration":979,"passed_time":7.596154484,"remaining_time":0.1550235609},
{"learn":[0.01738694466],"iteration":980,"passed_time":7.603641249,"remaining_time":0.1472672617},
{"learn":[0.01736833487],"iteration":981,"passed_time":7.61065601,"remaining_time":0.1395028597},
{"learn":[0.01735464432],"iteration":982,"passed_time":7.617495479,"remaining_time":0.1317369513},
{"learn":[0.01732493667],"iteration":983,"passed_time":7.624399406,"remaining_time":0.1239739741},
{"learn":[0.01730375027],"iteration":984,"passed_time":7.631527668,"remaining_time":0.1162161574},
{"learn":[0.01727953233],"iteration":985,"passed_time":7.638281094,"remaining_time":0.1084542955},
{"learn":[0.0172513154],"iteration":986,"passed_time":7.644811019,"remaining_time":0.1006915332},
{"learn":[0.01724046157],"iteration":987,"passed_time":7.651864989,"remaining_time":0.09293763144},
{"learn":[0.0172317727],"iteration":988,"passed_time":7.658610332,"remaining_time":0.08518171248},
{"learn":[0.01720834952],"iteration":989,"passed_time":7.665072922,"remaining_time":0.07742497901},
{"learn":[0.01718328857],"iteration":990,"passed_time":7.671767889,"remaining_time":0.06967296771},
{"learn":[0.01716524526],"iteration":991,"passed_time":7.677852769,"remaining_time":0.06191816749},
{"learn":[0.01714999306],"iteration":992,"passed_time":7.685012656,"remaining_time":0.05417430876},
{"learn":[0.01712267546],"iteration":993,"passed_time":7.691255829,"remaining_time":0.04642609152},
{"learn":[0.01710106913],"iteration":994,"passed_time":7.697694919,"remaining_time":0.03868188402},
{"learn":[0.01708525805],"iteration":995,"passed_time":7.704584763,"remaining_time":0.03094210748},
{"learn":[0.01706852709],"iteration":996,"passed_time":7.711387314,"remaining_time":0.02320377326},
{"learn":[0.01703828566],"iteration":997,"passed_time":7.717798363,"remaining_time":0.01546652979},
{"learn":[0.01701307604],"iteration":998,"passed_time":7.723794616,"remaining_time":0.007731526143},
{"learn":[0.01699183911],"iteration":999,"passed_time":7.730362,"remaining_time":0}
]}